Workbook
Name NativeTimeline_Date: #N/A
Name Slicer_City_Region: #N/A
Name Slicer_CustomerSegment: #N/A
Name Slicer_PurchaseChannel: #N/A

Sheet Dashboard
B2: 📊 MARKET RESEARCH & CUSTOMER SEGMENTATION DASHBOARD | FY 2025–26 | Apr 2025 – Mar 2026
B4: 👥 Total Customers | D4: 💰 Total Revenue (INR) | F4: 🛒 Avg Order Value (INR) | H4: 🔄 Repeat Customer % | J4: ⚠️ At-Risk Customers | L4: ⭐ Loyal Customers | N4: 📈 Avg Satisfaction
B5: ='KPI Summary'!B3 -> 200 | D5: ='KPI Summary'!B11 -> 10038773 | F5: ='KPI Summary'!B12 -> 9615.683 | H5: ='KPI Summary'!B24 -> 0.575 | J5: ='KPI Summary'!B33 -> 38 | L5: ='KPI Summary'!B27 -> 17 | N5: ='KPI Summary'!B42 -> 3.18625
B9: 📊 CHARTS & VISUALIZATIONS — Step 2: Insert Pivot Charts Here
B10: 📊 BAR CHART PLACEHOLDER Customers by Segment [ Insert Pivot Chart — Step 2 ] Source: tblFinal Rows: CustomerSegment Values: Count of CustomerID | I10: 📊 COLUMN CHART PLACEHOLDER Revenue by Segment [ Insert Pivot Chart — Step 2 ] Source: tblFinal Rows: CustomerSegment Values: Sum of RFM_Monetary
R25: x
B26: 🍩 DISTRIBUTION CHARTS — Step 2: Add Donut & Line Charts
B27: 🍩 DONUT CHART Customer Distribution [ Step 2 ] | F27: 📈 LINE CHART Monthly Revenue Trend [ Step 2 ] | J27: 📊 PIVOT TABLE Region-wise Analysis [ Step 2 ] | N27: ⚙️ SLICERS Segment Region Channel [ Step 2 ]
B41: 📋 KPI REFERENCE TABLE (Live — Updates from KPI Summary sheet)
B42: Metric | C42: Value | D42: Metric | E42: Value | F42: Metric | G42: Value | H42: Metric | I42: Value
B43: Total Customers | C43: ='KPI Summary'!B3 -> 200 | D43: Total Transactions | E43: ='KPI Summary'!B4 -> 1044 | F43: Total Revenue | G43: ='KPI Summary'!B11 -> 10038773 | H43: Avg AOV | I43: ='KPI Summary'!B12 -> 9615.683
B44: Repeat Customer % | C44: ='KPI Summary'!B24 -> 0.575 | D44: Loyal Customers | E44: ='KPI Summary'!B27 -> 17 | F44: At-Risk Customers | G44: ='KPI Summary'!B33 -> 38 | H44: Avg Satisfaction | I44: ='KPI Summary'!B42 -> 3.18625
B45: High Value Customers | C45: ='KPI Summary'!B25 -> 74 | D45: Online Revenue % | E45: ='KPI Summary'!B15 -> 0.47186255 | F45: Active Customers | G45: ='KPI Summary'!B22 -> 78 | H45: Low Engagement | I45: ='KPI Summary'!B35 -> 57
B48: 📋 SEGMENT PERFORMANCE SUMMARY (Live)
B49: Segment | C49: Customers | E49: Total Revenue | G49: Revenue % | I49: Avg Spend | K49: Status
B50: Loyal | C50: =COUNTIFS(tblFinal[CustomerSegment],B50) -> 17 | E50: =TEXT(IFERROR(SUMIFS(tblFinal[RFM_Monetary],tblFinal[CustomerSegment],B50),0),"#,##0") -> 15,25,892 | G50: {=TEXT(IFERROR(SUMPRODUCT((tblFinal[CustomerSegment]=B50)*SUMIFS(tblTransactions[Amount (INR)],tblTransactions[CustomerID],tblFinal[CustomerID]))/SUM(tblTransactions[Amount (INR)]),0),"0.0%")} -> 15.2% | I50: {=TEXT(IFERROR(SUMPRODUCT((tblFinal[CustomerSegment]=B50)*SUMIFS(tblTransactions[Amount (INR)],tblTransactions[CustomerID],tblFinal[CustomerID]))/COUNTIFS(tblFinal[CustomerSegment],B50),0),"#,##0")} -> 89,758 | K50: ⭐ Retain
B51: High Value | C51: =COUNTIFS(tblFinal[CustomerSegment],B51) -> 74 | E51: =TEXT(IFERROR(SUMIFS(tblFinal[RFM_Monetary],tblFinal[CustomerSegment],B51),0),"#,##0") -> 66,07,484 | G51: {=TEXT(IFERROR(SUMPRODUCT((tblFinal[CustomerSegment]=B51)*SUMIFS(tblTransactions[Amount (INR)],tblTransactions[CustomerID],tblFinal[CustomerID]))/SUM(tblTransactions[Amount (INR)]),0),"0.0%")} -> 65.8% | I51: {=TEXT(IFERROR(SUMPRODUCT((tblFinal[CustomerSegment]=B51)*SUMIFS(tblTransactions[Amount (INR)],tblTransactions[CustomerID],tblFinal[CustomerID]))/COUNTIFS(tblFinal[CustomerSegment],B51),0),"#,##0")} -> 89,290 | K51: 💎 Upsell
B52: At Risk | C52: =COUNTIFS(tblFinal[CustomerSegment],B52) -> 38 | E52: =TEXT(IFERROR(SUMIFS(tblFinal[RFM_Monetary],tblFinal[CustomerSegment],B52),0),"#,##0") -> 5,37,567 | G52: {=TEXT(IFERROR(SUMPRODUCT((tblFinal[CustomerSegment]=B52)*SUMIFS(tblTransactions[Amount (INR)],tblTransactions[CustomerID],tblFinal[CustomerID]))/SUM(tblTransactions[Amount (INR)]),0),"0.0%")} -> 5.4% | I52: {=TEXT(IFERROR(SUMPRODUCT((tblFinal[CustomerSegment]=B52)*SUMIFS(tblTransactions[Amount (INR)],tblTransactions[CustomerID],tblFinal[CustomerID]))/COUNTIFS(tblFinal[CustomerSegment],B52),0),"#,##0")} -> 14,147 | K52: ⚠️ Re-engage
B53: Bargain Seeker | C53: =COUNTIFS(tblFinal[CustomerSegment],B53) -> 8 | E53: =TEXT(IFERROR(SUMIFS(tblFinal[RFM_Monetary],tblFinal[CustomerSegment],B53),0),"#,##0") -> 1,84,330 | G53: {=TEXT(IFERROR(SUMPRODUCT((tblFinal[CustomerSegment]=B53)*SUMIFS(tblTransactions[Amount (INR)],tblTransactions[CustomerID],tblFinal[CustomerID]))/SUM(tblTransactions[Amount (INR)]),0),"0.0%")} -> 1.8% | I53: {=TEXT(IFERROR(SUMPRODUCT((tblFinal[CustomerSegment]=B53)*SUMIFS(tblTransactions[Amount (INR)],tblTransactions[CustomerID],tblFinal[CustomerID]))/COUNTIFS(tblFinal[CustomerSegment],B53),0),"#,##0")} -> 23,041 | K53: 🏷️ Nurture
B54: General | C54: =COUNTIFS(tblFinal[CustomerSegment],B54) -> 63 | E54: =TEXT(IFERROR(SUMIFS(tblFinal[RFM_Monetary],tblFinal[CustomerSegment],B54),0),"#,##0") -> 11,83,500 | G54: {=TEXT(IFERROR(SUMPRODUCT((tblFinal[CustomerSegment]=B54)*SUMIFS(tblTransactions[Amount (INR)],tblTransactions[CustomerID],tblFinal[CustomerID]))/SUM(tblTransactions[Amount (INR)]),0),"0.0%")} -> 11.8% | I54: {=TEXT(IFERROR(SUMPRODUCT((tblFinal[CustomerSegment]=B54)*SUMIFS(tblTransactions[Amount (INR)],tblTransactions[CustomerID],tblFinal[CustomerID]))/COUNTIFS(tblFinal[CustomerSegment],B54),0),"#,##0")} -> 18,786 | K54: 📌 Grow
B60: 📈 Pivot 5 — Analysis by Region | Source: tblTransactions
B61: Row Labels | C61: Count of CustomerID | D61: Sum of RFM_Monetary
B62: Ahmedabad | C62: 19 | D62: 666456
B63: Bangalore | C63: 14 | D63: 792765
B64: Bhopal | C64: 9 | D64: 479969
B65: Bhubaneswar | C65: 11 | D65: 663318
B66: Chandigarh | C66: 8 | D66: 445218
B67: Chennai | C67: 11 | D67: 751340
B68: Coimbatore | C68: 4 | D68: 207197
B69: Delhi | C69: 8 | D69: 275789
B70: Faridabad | C70: 2 | D70: 18490
B71: Gurgaon | C71: 2 | D71: 111010
B72: Hyderabad | C72: 8 | D72: 396008
B73: Indore | C73: 9 | D73: 405192
... B85: Grand Total | C85: 200 | D85: 10038773

Sheet Raw Data
A1: 📋 tblCustomers — Master Customer Data | O1: 💳 tblTransactions — Transaction Records | U1: 📝 tblSurvey — Customer Survey Responses
A2: CustomerID | B2: Name | C2: Gender | D2: Age | E2: City/Region | F2: IncomeRange | G2: Occupation | H2: JoinDate | I2: PurchaseChannel | J2: CustomerType | K2: EngagementLevel | L2: DiscountSensitivity | M2: LastPurchaseDate | N2: — | O2: TransactionID | P2: CustomerID | Q2: Date | R2: ProductCategory | S2: Amount (INR) | T2: — | U2: TxnMonth | V2: SurveyID | W2: CustomerID | X2: Satisfaction | Y2: PreferredChannel | Z2: RecommendationLikelihood
A3: C0001 | B3: Arjun Sharma | C3: Male | D3: 59 | E3: Noida | F3: 23278 | G3: Finance Analyst | H3: 45125 | I3: Online | J3: New | K3: Low | L3: High | M3: 46085 | O3: T00001 | P3: C0001 | Q3: 46085 | R3: Beauty | S3: 10900 | U3: =TEXT(tblTransactions[[#This Row],[Date]],"YYYY-MM") -> 2026-03 | V3: S0001 | W3: C0001 | X3: 4 | Y3: Online | Z3: 8
A4: C0002 | B4: Vikram Singh | C4: Male | D4: 53 | E4: Bangalore | F4: 97397 | G4: HR Manager | H4: 44627 | I4: Online | J4: New | K4: Medium | L4: Low | M4: 46043 | O4: T00002 | P4: C0002 | Q4: 46043 | R4: Grocery | S4: 3780 | U4: =TEXT(tblTransactions[[#This Row],[Date]],"YYYY-MM") -> 2026-01 | V4: S0002 | W4: C0002 | X4: 3 | Y4: Online | Z4: 6
A5: C0003 | B5: Rohan Mehta | C5: Male | D5: 31 | E5: Indore | F5: 74987 | G5: Doctor | H5: 45481 | I5: Online | J5: Returning | K5: Low | L5: High | M5: 45953 | O5: T00003 | P5: C0003 | Q5: 45942 | R5: Grocery | S5: 1950 | U5: =TEXT(tblTransactions[[#This Row],[Date]],"YYYY-MM") -> 2025-10 | V5: S0003 | W5: C0003 | X5: 4 | Y5: Online | Z5: 7
A6: C0004 | B6: Nikhil Gupta | C6: Male | D6: 46 | E6: Jaipur | F6: 56421 | G6: Teacher | H6: 45002 | I6: Offline | J6: New | K6: Low | L6: Low | M6: 46074 | O6: T00004 | P6: C0003 | Q6: 45953 | R6: Grocery | S6: 3430 | U6: =TEXT(tblTransactions[[#This Row],[Date]],"YYYY-MM") -> 2025-10 | V6: S0004 | W6: C0004 | X6: 3 | Y6: Offline | Z6: 6
A7: C0005 | B7: Amit Verma | C7: Male | D7: 41 | E7: Bhubaneswar | F7: 54671 | G7: Operations Manager | H7: 44650 | I7: Offline | J7: Returning | K7: High | L7: Medium | M7: 46013 | O7: T00005 | P7: C0004 | Q7: 46074 | R7: Electronics | S7: 12070 | U7: =TEXT(tblTransactions[[#This Row],[Date]],"YYYY-MM") -> 2026-02 | V7: S0005 | W7: C0005 | X7: 4 | Y7: Offline | Z7: 4
A8: C0006 | B8: Suresh Kumar | C8: Male | D8: 54 | E8: Kolkata | F8: 128711 | G8: Consultant | H8: 45302 | I8: Online | J8: Returning | K8: Low | L8: Low | M8: 45960 | O8: T00006 | P8: C0005 | Q8: 45933 | R8: Home Decor | S8: 1470 | U8: =TEXT(tblTransactions[[#This Row],[Date]],"YYYY-MM") -> 2025-10 | V8: S0006 | W8: C0006 | X8: 4 | Y8: Online | Z8: 7
A9: C0007 | B9: Rajesh Patel | C9: Male | D9: 37 | E9: Bangalore | F9: 132108 | G9: Doctor | H9: 44768 | I9: Online | J9: Returning | K9: High | L9: Low | M9: 45900 | O9: T00007 | P9: C0005 | Q9: 46003 | R9: Clothing | S9: 1730 | U9: =TEXT(tblTransactions[[#This Row],[Date]],"YYYY-MM") -> 2025-12 | V9: S0007 | W9: C0007 | X9: 4 | Y9: Online | Z9: 4
A10: C0008 | B10: Aditya Joshi | C10: Male | D10: 41 | E10: Hyderabad | F10: 107841 | G10: Business Owner | H10: 44708 | I10: Offline | J10: New | K10: Medium | L10: Low | M10: 46032 | O10: T00008 | P10: C0005 | Q10: 45884 | R10: Home Decor | S10: 1730 | U10: =TEXT(tblTransactions[[#This Row],[Date]],"YYYY-MM") -> 2025-08 | V10: S0008 | W10: C0008 | X10: 1 | Y10: Offline | Z10: 5
A11: C0009 | B11: Karan Kapoor | C11: Male | D11: 43 | E11: Ahmedabad | F11: 149698 | G11: Entrepreneur | H11: 45702 | I11: Online | J11: New | K11: High | L11: Low | M11: 46033 | O11: T00009 | P11: C0005 | Q11: 45815 | R11: Sports | S11: 9740 | U11: =TEXT(tblTransactions[[#This Row],[Date]],"YYYY-MM") -> 2025-06 | V11: S0009 | W11: C0009 | X11: 4 | Y11: Online | Z11: 9
A12: C0010 | B12: Deepak Nair | C12: Male | D12: 21 | E12: Jaipur | F12: 72581 | G12: Business Owner | H12: 44697 | I12: Online | J12: Returning | K12: High | L12: Medium | M12: 46085 | O12: T00010 | P12: C0005 | Q12: 45996 | R12: Electronics | S12: 3090 | U12: =TEXT(tblTransactions[[#This Row],[Date]],"YYYY-MM") -> 2025-12 | V12: S0010 | W12: C0010 | X12: 3 | Y12: Online | Z12: 6
A13: C0011 | B13: Manish Tiwari | C13: Male | D13: 60 | E13: Bhopal | F13: 71856 | G13: Entrepreneur | H13: 45501 | I13: Online | J13: New | K13: Medium | L13: Medium | M13: 46059 | O13: T00011 | P13: C0005 | Q13: 45762 | R13: Clothing | S13: 13260 | U13: =TEXT(tblTransactions[[#This Row],[Date]],"YYYY-MM") -> 2025-04 | V13: S0011 | W13: C0011 | X13: 4 | Y13: Online | Z13: 8
A14: C0012 | B14: Gaurav Saxena | C14: Male | D14: 56 | E14: Lucknow | F14: 137679 | G14: Retail Manager | H14: 45379 | I14: Online | J14: Returning | K14: Low | L14: Medium | M14: 45965 | O14: T00012 | P14: C0005 | Q14: 45829 | R14: Grocery | S14: 3740 | U14: =TEXT(tblTransactions[[#This Row],[Date]],"YYYY-MM") -> 2025-06 | V14: S0012 | W14: C0012 | X14: 4 | Y14: Online | Z14: 8
... A202: C0200 | B202: Manoj Pillai | C202: Male | D202: 35 | E202: Lucknow | F202: 73373 | G202: Consultant | H202: 45578 | I202: Offline | J202: Returning | K202: Medium | L202: Low | M202: 45751 | O202: T00200 | P202: C0045 | Q202: 45943 | R202: Home Decor | S202: 4130 | U202: =TEXT(tblTransactions[[#This Row],[Date]],"YYYY-MM") -> 2025-10 | V202: S0200 | W202: C0200 | X202: 1 | Y202: Online | Z202: 10
O203: T00201 | P203: C0045 | Q203: 46018 | R203: Clothing | S203: 2970 | U203: =TEXT(tblTransactions[[#This Row],[Date]],"YYYY-MM") -> 2025-12
O204: T00202 | P204: C0045 | Q204: 46057 | R204: Clothing | S204: 5680 | U204: =TEXT(tblTransactions[[#This Row],[Date]],"YYYY-MM") -> 2026-02
O205: T00203 | P205: C0045 | Q205: 45876 | R205: Grocery | S205: 10710 | U205: =TEXT(tblTransactions[[#This Row],[Date]],"YYYY-MM") -> 2025-08
O206: T00204 | P206: C0045 | Q206: 46031 | R206: Electronics | S206: 6040 | U206: =TEXT(tblTransactions[[#This Row],[Date]],"YYYY-MM") -> 2026-01
O207: T00205 | P207: C0045 | Q207: 46080 | R207: Electronics | S207: 3570 | U207: =TEXT(tblTransactions[[#This Row],[Date]],"YYYY-MM") -> 2026-02
O208: T00206 | P208: C0046 | Q208: 45823 | R208: Beauty | S208: 1770 | U208: =TEXT(tblTransactions[[#This Row],[Date]],"YYYY-MM") -> 2025-06
O209: T00207 | P209: C0046 | Q209: 45794 | R209: Beauty | S209: 7680 | U209: =TEXT(tblTransactions[[#This Row],[Date]],"YYYY-MM") -> 2025-05
O210: T00208 | P210: C0046 | Q210: 45926 | R210: Electronics | S210: 3730 | U210: =TEXT(tblTransactions[[#This Row],[Date]],"YYYY-MM") -> 2025-09
O211: T00209 | P211: C0046 | Q211: 45960 | R211: Clothing | S211: 10980 | U211: =TEXT(tblTransactions[[#This Row],[Date]],"YYYY-MM") -> 2025-10
O212: T00210 | P212: C0046 | Q212: 45945 | R212: Electronics | S212: 6140 | U212: =TEXT(tblTransactions[[#This Row],[Date]],"YYYY-MM") -> 2025-10
O213: T00211 | P213: C0046 | Q213: 45939 | R213: Electronics | S213: 5030 | U213: =TEXT(tblTransactions[[#This Row],[Date]],"YYYY-MM") -> 2025-10
O214: T00212 | P214: C0046 | Q214: 45919 | R214: Clothing | S214: 8990 | U214: =TEXT(tblTransactions[[#This Row],[Date]],"YYYY-MM") -> 2025-09
... O1046: T01045 | P1046: C0200 | Q1046: 45955 | R1046: Home Decor | S1046: 6544 | U1046: =TEXT(tblTransactions[[#This Row],[Date]],"YYYY-MM") -> 2025-10

Sheet Cleaned Data
A1: 🧹 tblClean — Cleaned Customer Data with Derived Columns (Formula-Driven from tblCustomers)
A2: CustomerID | B2: Name (Cleaned) | C2: Gender | D2: Age | E2: City/Region (Cleaned) | F2: IncomeRange | G2: Occupation (Cleaned) | H2: JoinDate | I2: PurchaseChannel | J2: CustomerType | K2: EngagementLevel | L2: DiscountSensitivity | M2: LastPurchaseDate | N2: AgeGroup | O2: IncomeBracket | P2: DayOfJoin | Q2: IsWeekend_Join | R2: MonthsAsCustomer | S2: DataFlag
A3: =IFERROR(TRIM(tblCustomers[[#This Row],[CustomerID]]),"") -> C0001 | B3: =IFERROR(PROPER(TRIM(tblCustomers[[#This Row],[Name]])),"") -> Arjun Sharma | C3: =IFERROR(PROPER(TRIM(tblCustomers[[#This Row],[Gender]])),"") -> Male | D3: =IFERROR(tblCustomers[[#This Row],[Age]],"") -> 59 | E3: =IFERROR(PROPER(TRIM(tblCustomers[[#This Row],[City/Region]])),"") -> Noida | F3: =IFERROR(tblCustomers[[#This Row],[IncomeRange]],"") -> 23278 | G3: =IFERROR(PROPER(TRIM(tblCustomers[[#This Row],[Occupation]])),"") -> Finance Analyst | H3: =IFERROR(tblCustomers[[#This Row],[JoinDate]],"") -> 45125 | I3: =IFERROR(PROPER(TRIM(tblCustomers[[#This Row],[PurchaseChannel]])),"") -> Online | J3: =IFERROR(PROPER(TRIM(tblCustomers[[#This Row],[CustomerType]])),"") -> New | K3: =IFERROR(PROPER(TRIM(tblCustomers[[#This Row],[EngagementLevel]])),"") -> Low | L3: =IFERROR(PROPER(TRIM(tblCustomers[[#This Row],[DiscountSensitivity]])),"") -> High | M3: =IFERROR(tblCustomers[[#This Row],[LastPurchaseDate]],"") -> 46085 | N3: =IFERROR(IF(tblCustomers[[#This Row],[Age]]<25,"<25",IF(tblCustomers[[#This Row],[Age]]<40,"25-39",IF(tblCustomers[[#This Row],[Age]]<55,"40-54","55+"))),"N/A") -> 55+ | O3: =IFERROR(IF(tblCustomers[[#This Row],[IncomeRange]]<25000,"Low",IF(tblCustomers[[#This Row],[IncomeRange]]<75000,"Mid","High")),"N/A") -> Low | P3: =IFERROR(TEXT(tblCustomers[[#This Row],[JoinDate]],"DDDD"),"") -> Tuesday | Q3: =IFERROR(IF(WEEKDAY(tblCustomers[[#This Row],[JoinDate]],2)>=6,TRUE(),FALSE()),FALSE()) -> FALSE | R3: =IFERROR(DATEDIF(tblCustomers[[#This Row],[JoinDate]],TODAY(),"M"),0) -> 32 | S3: =IFERROR(IF(AND(tblCustomers[[#This Row],[Age]]>=18,tblCustomers[[#This Row],[IncomeRange]]>0,tblCustomers[[#This Row],[CustomerID]]<>""),"OK","CHECK"),"CHECK") -> OK
A4: =IFERROR(TRIM(tblCustomers[[#This Row],[CustomerID]]),"") -> C0002 | B4: =IFERROR(PROPER(TRIM(tblCustomers[[#This Row],[Name]])),"") -> Vikram Singh | C4: =IFERROR(PROPER(TRIM(tblCustomers[[#This Row],[Gender]])),"") -> Male | D4: =IFERROR(tblCustomers[[#This Row],[Age]],"") -> 53 | E4: =IFERROR(PROPER(TRIM(tblCustomers[[#This Row],[City/Region]])),"") -> Bangalore | F4: =IFERROR(tblCustomers[[#This Row],[IncomeRange]],"") -> 97397 | G4: =IFERROR(PROPER(TRIM(tblCustomers[[#This Row],[Occupation]])),"") -> Hr Manager | H4: =IFERROR(tblCustomers[[#This Row],[JoinDate]],"") -> 44627 | I4: =IFERROR(PROPER(TRIM(tblCustomers[[#This Row],[PurchaseChannel]])),"") -> Online | J4: =IFERROR(PROPER(TRIM(tblCustomers[[#This Row],[CustomerType]])),"") -> New | K4: =IFERROR(PROPER(TRIM(tblCustomers[[#This Row],[EngagementLevel]])),"") -> Medium | L4: =IFERROR(PROPER(TRIM(tblCustomers[[#This Row],[DiscountSensitivity]])),"") -> Low | M4: =IFERROR(tblCustomers[[#This Row],[LastPurchaseDate]],"") -> 46043 | N4: =IFERROR(IF(tblCustomers[[#This Row],[Age]]<25,"<25",IF(tblCustomers[[#This Row],[Age]]<40,"25-39",IF(tblCustomers[[#This Row],[Age]]<55,"40-54","55+"))),"N/A") -> 40-54 | O4: =IFERROR(IF(tblCustomers[[#This Row],[IncomeRange]]<25000,"Low",IF(tblCustomers[[#This Row],[IncomeRange]]<75000,"Mid","High")),"N/A") -> High | P4: =IFERROR(TEXT(tblCustomers[[#This Row],[JoinDate]],"DDDD"),"") -> Monday | Q4: =IFERROR(IF(WEEKDAY(tblCustomers[[#This Row],[JoinDate]],2)>=6,TRUE(),FALSE()),FALSE()) -> FALSE | R4: =IFERROR(DATEDIF(tblCustomers[[#This Row],[JoinDate]],TODAY(),"M"),0) -> 49 | S4: =IFERROR(IF(AND(tblCustomers[[#This Row],[Age]]>=18,tblCustomers[[#This Row],[IncomeRange]]>0,tblCustomers[[#This Row],[CustomerID]]<>""),"OK","CHECK"),"CHECK") -> OK
A5: =IFERROR(TRIM(tblCustomers[[#This Row],[CustomerID]]),"") -> C0003 | B5: =IFERROR(PROPER(TRIM(tblCustomers[[#This Row],[Name]])),"") -> Rohan Mehta | C5: =IFERROR(PROPER(TRIM(tblCustomers[[#This Row],[Gender]])),"") -> Male | D5: =IFERROR(tblCustomers[[#This Row],[Age]],"") -> 31 | E5: =IFERROR(PROPER(TRIM(tblCustomers[[#This Row],[City/Region]])),"") -> Indore | F5: =IFERROR(tblCustomers[[#This Row],[IncomeRange]],"") -> 74987 | G5: =IFERROR(PROPER(TRIM(tblCustomers[[#This Row],[Occupation]])),"") -> Doctor | H5: =IFERROR(tblCustomers[[#This Row],[JoinDate]],"") -> 45481 | I5: =IFERROR(PROPER(TRIM(tblCustomers[[#This Row],[PurchaseChannel]])),"") -> Online | J5: =IFERROR(PROPER(TRIM(tblCustomers[[#This Row],[CustomerType]])),"") -> Returning | K5: =IFERROR(PROPER(TRIM(tblCustomers[[#This Row],[EngagementLevel]])),"") -> Low | L5: =IFERROR(PROPER(TRIM(tblCustomers[[#This Row],[DiscountSensitivity]])),"") -> High | M5: =IFERROR(tblCustomers[[#This Row],[LastPurchaseDate]],"") -> 45953 | N5: =IFERROR(IF(tblCustomers[[#This Row],[Age]]<25,"<25",IF(tblCustomers[[#This Row],[Age]]<40,"25-39",IF(tblCustomers[[#This Row],[Age]]<55,"40-54","55+"))),"N/A") -> 25-39 | O5: =IFERROR(IF(tblCustomers[[#This Row],[IncomeRange]]<25000,"Low",IF(tblCustomers[[#This Row],[IncomeRange]]<75000,"Mid","High")),"N/A") -> Mid | P5: =IFERROR(TEXT(tblCustomers[[#This Row],[JoinDate]],"DDDD"),"") -> Monday | Q5: =IFERROR(IF(WEEKDAY(tblCustomers[[#This Row],[JoinDate]],2)>=6,TRUE(),FALSE()),FALSE()) -> FALSE | R5: =IFERROR(DATEDIF(tblCustomers[[#This Row],[JoinDate]],TODAY(),"M"),0) -> 21 | S5: =IFERROR(IF(AND(tblCustomers[[#This Row],[Age]]>=18,tblCustomers[[#This Row],[IncomeRange]]>0,tblCustomers[[#This Row],[CustomerID]]<>""),"OK","CHECK"),"CHECK") -> OK
A6: =IFERROR(TRIM(tblCustomers[[#This Row],[CustomerID]]),"") -> C0004 | B6: =IFERROR(PROPER(TRIM(tblCustomers[[#This Row],[Name]])),"") -> Nikhil Gupta | C6: =IFERROR(PROPER(TRIM(tblCustomers[[#This Row],[Gender]])),"") -> Male | D6: =IFERROR(tblCustomers[[#This Row],[Age]],"") -> 46 | E6: =IFERROR(PROPER(TRIM(tblCustomers[[#This Row],[City/Region]])),"") -> Jaipur | F6: =IFERROR(tblCustomers[[#This Row],[IncomeRange]],"") -> 56421 | G6: =IFERROR(PROPER(TRIM(tblCustomers[[#This Row],[Occupation]])),"") -> Teacher | H6: =IFERROR(tblCustomers[[#This Row],[JoinDate]],"") -> 45002 | I6: =IFERROR(PROPER(TRIM(tblCustomers[[#This Row],[PurchaseChannel]])),"") -> Offline | J6: =IFERROR(PROPER(TRIM(tblCustomers[[#This Row],[CustomerType]])),"") -> New | K6: =IFERROR(PROPER(TRIM(tblCustomers[[#This Row],[EngagementLevel]])),"") -> Low | L6: =IFERROR(PROPER(TRIM(tblCustomers[[#This Row],[DiscountSensitivity]])),"") -> Low | M6: =IFERROR(tblCustomers[[#This Row],[LastPurchaseDate]],"") -> 46074 | N6: =IFERROR(IF(tblCustomers[[#This Row],[Age]]<25,"<25",IF(tblCustomers[[#This Row],[Age]]<40,"25-39",IF(tblCustomers[[#This Row],[Age]]<55,"40-54","55+"))),"N/A") -> 40-54 | O6: =IFERROR(IF(tblCustomers[[#This Row],[IncomeRange]]<25000,"Low",IF(tblCustomers[[#This Row],[IncomeRange]]<75000,"Mid","High")),"N/A") -> Mid | P6: =IFERROR(TEXT(tblCustomers[[#This Row],[JoinDate]],"DDDD"),"") -> Friday | Q6: =IFERROR(IF(WEEKDAY(tblCustomers[[#This Row],[JoinDate]],2)>=6,TRUE(),FALSE()),FALSE()) -> FALSE | R6: =IFERROR(DATEDIF(tblCustomers[[#This Row],[JoinDate]],TODAY(),"M"),0) -> 36 | S6: =IFERROR(IF(AND(tblCustomers[[#This Row],[Age]]>=18,tblCustomers[[#This Row],[IncomeRange]]>0,tblCustomers[[#This Row],[CustomerID]]<>""),"OK","CHECK"),"CHECK") -> OK
A7: =IFERROR(TRIM(tblCustomers[[#This Row],[CustomerID]]),"") -> C0005 | B7: =IFERROR(PROPER(TRIM(tblCustomers[[#This Row],[Name]])),"") -> Amit Verma | C7: =IFERROR(PROPER(TRIM(tblCustomers[[#This Row],[Gender]])),"") -> Male | D7: =IFERROR(tblCustomers[[#This Row],[Age]],"") -> 41 | E7: =IFERROR(PROPER(TRIM(tblCustomers[[#This Row],[City/Region]])),"") -> Bhubaneswar | F7: =IFERROR(tblCustomers[[#This Row],[IncomeRange]],"") -> 54671 | G7: =IFERROR(PROPER(TRIM(tblCustomers[[#This Row],[Occupation]])),"") -> Operations Manager | H7: =IFERROR(tblCustomers[[#This Row],[JoinDate]],"") -> 44650 | I7: =IFERROR(PROPER(TRIM(tblCustomers[[#This Row],[PurchaseChannel]])),"") -> Offline | J7: =IFERROR(PROPER(TRIM(tblCustomers[[#This Row],[CustomerType]])),"") -> Returning | K7: =IFERROR(PROPER(TRIM(tblCustomers[[#This Row],[EngagementLevel]])),"") -> High | L7: =IFERROR(PROPER(TRIM(tblCustomers[[#This Row],[DiscountSensitivity]])),"") -> Medium | M7: =IFERROR(tblCustomers[[#This Row],[LastPurchaseDate]],"") -> 46013 | N7: =IFERROR(IF(tblCustomers[[#This Row],[Age]]<25,"<25",IF(tblCustomers[[#This Row],[Age]]<40,"25-39",IF(tblCustomers[[#This Row],[Age]]<55,"40-54","55+"))),"N/A") -> 40-54 | O7: =IFERROR(IF(tblCustomers[[#This Row],[IncomeRange]]<25000,"Low",IF(tblCustomers[[#This Row],[IncomeRange]]<75000,"Mid","High")),"N/A") -> Mid | P7: =IFERROR(TEXT(tblCustomers[[#This Row],[JoinDate]],"DDDD"),"") -> Wednesday | Q7: =IFERROR(IF(WEEKDAY(tblCustomers[[#This Row],[JoinDate]],2)>=6,TRUE(),FALSE()),FALSE()) -> FALSE | R7: =IFERROR(DATEDIF(tblCustomers[[#This Row],[JoinDate]],TODAY(),"M"),0) -> 48 | S7: =IFERROR(IF(AND(tblCustomers[[#This Row],[Age]]>=18,tblCustomers[[#This Row],[IncomeRange]]>0,tblCustomers[[#This Row],[CustomerID]]<>""),"OK","CHECK"),"CHECK") -> OK
A8: =IFERROR(TRIM(tblCustomers[[#This Row],[CustomerID]]),"") -> C0006 | B8: =IFERROR(PROPER(TRIM(tblCustomers[[#This Row],[Name]])),"") -> Suresh Kumar | C8: =IFERROR(PROPER(TRIM(tblCustomers[[#This Row],[Gender]])),"") -> Male | D8: =IFERROR(tblCustomers[[#This Row],[Age]],"") -> 54 | E8: =IFERROR(PROPER(TRIM(tblCustomers[[#This Row],[City/Region]])),"") -> Kolkata | F8: =IFERROR(tblCustomers[[#This Row],[IncomeRange]],"") -> 128711 | G8: =IFERROR(PROPER(TRIM(tblCustomers[[#This Row],[Occupation]])),"") -> Consultant | H8: =IFERROR(tblCustomers[[#This Row],[JoinDate]],"") -> 45302 | I8: =IFERROR(PROPER(TRIM(tblCustomers[[#This Row],[PurchaseChannel]])),"") -> Online | J8: =IFERROR(PROPER(TRIM(tblCustomers[[#This Row],[CustomerType]])),"") -> Returning | K8: =IFERROR(PROPER(TRIM(tblCustomers[[#This Row],[EngagementLevel]])),"") -> Low | L8: =IFERROR(PROPER(TRIM(tblCustomers[[#This Row],[DiscountSensitivity]])),"") -> Low | M8: =IFERROR(tblCustomers[[#This Row],[LastPurchaseDate]],"") -> 45960 | N8: =IFERROR(IF(tblCustomers[[#This Row],[Age]]<25,"<25",IF(tblCustomers[[#This Row],[Age]]<40,"25-39",IF(tblCustomers[[#This Row],[Age]]<55,"40-54","55+"))),"N/A") -> 40-54 | O8: =IFERROR(IF(tblCustomers[[#This Row],[IncomeRange]]<25000,"Low",IF(tblCustomers[[#This Row],[IncomeRange]]<75000,"Mid","High")),"N/A") -> High | P8: =IFERROR(TEXT(tblCustomers[[#This Row],[JoinDate]],"DDDD"),"") -> Thursday | Q8: =IFERROR(IF(WEEKDAY(tblCustomers[[#This Row],[JoinDate]],2)>=6,TRUE(),FALSE()),FALSE()) -> FALSE | R8: =IFERROR(DATEDIF(tblCustomers[[#This Row],[JoinDate]],TODAY(),"M"),0) -> 27 | S8: =IFERROR(IF(AND(tblCustomers[[#This Row],[Age]]>=18,tblCustomers[[#This Row],[IncomeRange]]>0,tblCustomers[[#This Row],[CustomerID]]<>""),"OK","CHECK"),"CHECK") -> OK
A9: =IFERROR(TRIM(tblCustomers[[#This Row],[CustomerID]]),"") -> C0007 | B9: =IFERROR(PROPER(TRIM(tblCustomers[[#This Row],[Name]])),"") -> Rajesh Patel | C9: =IFERROR(PROPER(TRIM(tblCustomers[[#This Row],[Gender]])),"") -> Male | D9: =IFERROR(tblCustomers[[#This Row],[Age]],"") -> 37 | E9: =IFERROR(PROPER(TRIM(tblCustomers[[#This Row],[City/Region]])),"") -> Bangalore | F9: =IFERROR(tblCustomers[[#This Row],[IncomeRange]],"") -> 132108 | G9: =IFERROR(PROPER(TRIM(tblCustomers[[#This Row],[Occupation]])),"") -> Doctor | H9: =IFERROR(tblCustomers[[#This Row],[JoinDate]],"") -> 44768 | I9: =IFERROR(PROPER(TRIM(tblCustomers[[#This Row],[PurchaseChannel]])),"") -> Online | J9: =IFERROR(PROPER(TRIM(tblCustomers[[#This Row],[CustomerType]])),"") -> Returning | K9: =IFERROR(PROPER(TRIM(tblCustomers[[#This Row],[EngagementLevel]])),"") -> High | L9: =IFERROR(PROPER(TRIM(tblCustomers[[#This Row],[DiscountSensitivity]])),"") -> Low | M9: =IFERROR(tblCustomers[[#This Row],[LastPurchaseDate]],"") -> 45900 | N9: =IFERROR(IF(tblCustomers[[#This Row],[Age]]<25,"<25",IF(tblCustomers[[#This Row],[Age]]<40,"25-39",IF(tblCustomers[[#This Row],[Age]]<55,"40-54","55+"))),"N/A") -> 25-39 | O9: =IFERROR(IF(tblCustomers[[#This Row],[IncomeRange]]<25000,"Low",IF(tblCustomers[[#This Row],[IncomeRange]]<75000,"Mid","High")),"N/A") -> High | P9: =IFERROR(TEXT(tblCustomers[[#This Row],[JoinDate]],"DDDD"),"") -> Tuesday | Q9: =IFERROR(IF(WEEKDAY(tblCustomers[[#This Row],[JoinDate]],2)>=6,TRUE(),FALSE()),FALSE()) -> FALSE | R9: =IFERROR(DATEDIF(tblCustomers[[#This Row],[JoinDate]],TODAY(),"M"),0) -> 44 | S9: =IFERROR(IF(AND(tblCustomers[[#This Row],[Age]]>=18,tblCustomers[[#This Row],[IncomeRange]]>0,tblCustomers[[#This Row],[CustomerID]]<>""),"OK","CHECK"),"CHECK") -> OK
A10: =IFERROR(TRIM(tblCustomers[[#This Row],[CustomerID]]),"") -> C0008 | B10: =IFERROR(PROPER(TRIM(tblCustomers[[#This Row],[Name]])),"") -> Aditya Joshi | C10: =IFERROR(PROPER(TRIM(tblCustomers[[#This Row],[Gender]])),"") -> Male | D10: =IFERROR(tblCustomers[[#This Row],[Age]],"") -> 41 | E10: =IFERROR(PROPER(TRIM(tblCustomers[[#This Row],[City/Region]])),"") -> Hyderabad | F10: =IFERROR(tblCustomers[[#This Row],[IncomeRange]],"") -> 107841 | G10: =IFERROR(PROPER(TRIM(tblCustomers[[#This Row],[Occupation]])),"") -> Business Owner | H10: =IFERROR(tblCustomers[[#This Row],[JoinDate]],"") -> 44708 | I10: =IFERROR(PROPER(TRIM(tblCustomers[[#This Row],[PurchaseChannel]])),"") -> Offline | J10: =IFERROR(PROPER(TRIM(tblCustomers[[#This Row],[CustomerType]])),"") -> New | K10: =IFERROR(PROPER(TRIM(tblCustomers[[#This Row],[EngagementLevel]])),"") -> Medium | L10: =IFERROR(PROPER(TRIM(tblCustomers[[#This Row],[DiscountSensitivity]])),"") -> Low | M10: =IFERROR(tblCustomers[[#This Row],[LastPurchaseDate]],"") -> 46032 | N10: =IFERROR(IF(tblCustomers[[#This Row],[Age]]<25,"<25",IF(tblCustomers[[#This Row],[Age]]<40,"25-39",IF(tblCustomers[[#This Row],[Age]]<55,"40-54","55+"))),"N/A") -> 40-54 | O10: =IFERROR(IF(tblCustomers[[#This Row],[IncomeRange]]<25000,"Low",IF(tblCustomers[[#This Row],[IncomeRange]]<75000,"Mid","High")),"N/A") -> High | P10: =IFERROR(TEXT(tblCustomers[[#This Row],[JoinDate]],"DDDD"),"") -> Friday | Q10: =IFERROR(IF(WEEKDAY(tblCustomers[[#This Row],[JoinDate]],2)>=6,TRUE(),FALSE()),FALSE()) -> FALSE | R10: =IFERROR(DATEDIF(tblCustomers[[#This Row],[JoinDate]],TODAY(),"M"),0) -> 46 | S10: =IFERROR(IF(AND(tblCustomers[[#This Row],[Age]]>=18,tblCustomers[[#This Row],[IncomeRange]]>0,tblCustomers[[#This Row],[CustomerID]]<>""),"OK","CHECK"),"CHECK") -> OK
A11: =IFERROR(TRIM(tblCustomers[[#This Row],[CustomerID]]),"") -> C0009 | B11: =IFERROR(PROPER(TRIM(tblCustomers[[#This Row],[Name]])),"") -> Karan Kapoor | C11: =IFERROR(PROPER(TRIM(tblCustomers[[#This Row],[Gender]])),"") -> Male | D11: =IFERROR(tblCustomers[[#This Row],[Age]],"") -> 43 | E11: =IFERROR(PROPER(TRIM(tblCustomers[[#This Row],[City/Region]])),"") -> Ahmedabad | F11: =IFERROR(tblCustomers[[#This Row],[IncomeRange]],"") -> 149698 | G11: =IFERROR(PROPER(TRIM(tblCustomers[[#This Row],[Occupation]])),"") -> Entrepreneur | H11: =IFERROR(tblCustomers[[#This Row],[JoinDate]],"") -> 45702 | I11: =IFERROR(PROPER(TRIM(tblCustomers[[#This Row],[PurchaseChannel]])),"") -> Online | J11: =IFERROR(PROPER(TRIM(tblCustomers[[#This Row],[CustomerType]])),"") -> New | K11: =IFERROR(PROPER(TRIM(tblCustomers[[#This Row],[EngagementLevel]])),"") -> High | L11: =IFERROR(PROPER(TRIM(tblCustomers[[#This Row],[DiscountSensitivity]])),"") -> Low | M11: =IFERROR(tblCustomers[[#This Row],[LastPurchaseDate]],"") -> 46033 | N11: =IFERROR(IF(tblCustomers[[#This Row],[Age]]<25,"<25",IF(tblCustomers[[#This Row],[Age]]<40,"25-39",IF(tblCustomers[[#This Row],[Age]]<55,"40-54","55+"))),"N/A") -> 40-54 | O11: =IFERROR(IF(tblCustomers[[#This Row],[IncomeRange]]<25000,"Low",IF(tblCustomers[[#This Row],[IncomeRange]]<75000,"Mid","High")),"N/A") -> High | P11: =IFERROR(TEXT(tblCustomers[[#This Row],[JoinDate]],"DDDD"),"") -> Friday | Q11: =IFERROR(IF(WEEKDAY(tblCustomers[[#This Row],[JoinDate]],2)>=6,TRUE(),FALSE()),FALSE()) -> FALSE | R11: =IFERROR(DATEDIF(tblCustomers[[#This Row],[JoinDate]],TODAY(),"M"),0) -> 13 | S11: =IFERROR(IF(AND(tblCustomers[[#This Row],[Age]]>=18,tblCustomers[[#This Row],[IncomeRange]]>0,tblCustomers[[#This Row],[CustomerID]]<>""),"OK","CHECK"),"CHECK") -> OK
A12: =IFERROR(TRIM(tblCustomers[[#This Row],[CustomerID]]),"") -> C0010 | B12: =IFERROR(PROPER(TRIM(tblCustomers[[#This Row],[Name]])),"") -> Deepak Nair | C12: =IFERROR(PROPER(TRIM(tblCustomers[[#This Row],[Gender]])),"") -> Male | D12: =IFERROR(tblCustomers[[#This Row],[Age]],"") -> 21 | E12: =IFERROR(PROPER(TRIM(tblCustomers[[#This Row],[City/Region]])),"") -> Jaipur | F12: =IFERROR(tblCustomers[[#This Row],[IncomeRange]],"") -> 72581 | G12: =IFERROR(PROPER(TRIM(tblCustomers[[#This Row],[Occupation]])),"") -> Business Owner | H12: =IFERROR(tblCustomers[[#This Row],[JoinDate]],"") -> 44697 | I12: =IFERROR(PROPER(TRIM(tblCustomers[[#This Row],[PurchaseChannel]])),"") -> Online | J12: =IFERROR(PROPER(TRIM(tblCustomers[[#This Row],[CustomerType]])),"") -> Returning | K12: =IFERROR(PROPER(TRIM(tblCustomers[[#This Row],[EngagementLevel]])),"") -> High | L12: =IFERROR(PROPER(TRIM(tblCustomers[[#This Row],[DiscountSensitivity]])),"") -> Medium | M12: =IFERROR(tblCustomers[[#This Row],[LastPurchaseDate]],"") -> 46085 | N12: =IFERROR(IF(tblCustomers[[#This Row],[Age]]<25,"<25",IF(tblCustomers[[#This Row],[Age]]<40,"25-39",IF(tblCustomers[[#This Row],[Age]]<55,"40-54","55+"))),"N/A") -> <25 | O12: =IFERROR(IF(tblCustomers[[#This Row],[IncomeRange]]<25000,"Low",IF(tblCustomers[[#This Row],[IncomeRange]]<75000,"Mid","High")),"N/A") -> Mid | P12: =IFERROR(TEXT(tblCustomers[[#This Row],[JoinDate]],"DDDD"),"") -> Monday | Q12: =IFERROR(IF(WEEKDAY(tblCustomers[[#This Row],[JoinDate]],2)>=6,TRUE(),FALSE()),FALSE()) -> FALSE | R12: =IFERROR(DATEDIF(tblCustomers[[#This Row],[JoinDate]],TODAY(),"M"),0) -> 46 | S12: =IFERROR(IF(AND(tblCustomers[[#This Row],[Age]]>=18,tblCustomers[[#This Row],[IncomeRange]]>0,tblCustomers[[#This Row],[CustomerID]]<>""),"OK","CHECK"),"CHECK") -> OK
A13: =IFERROR(TRIM(tblCustomers[[#This Row],[CustomerID]]),"") -> C0011 | B13: =IFERROR(PROPER(TRIM(tblCustomers[[#This Row],[Name]])),"") -> Manish Tiwari | C13: =IFERROR(PROPER(TRIM(tblCustomers[[#This Row],[Gender]])),"") -> Male | D13: =IFERROR(tblCustomers[[#This Row],[Age]],"") -> 60 | E13: =IFERROR(PROPER(TRIM(tblCustomers[[#This Row],[City/Region]])),"") -> Bhopal | F13: =IFERROR(tblCustomers[[#This Row],[IncomeRange]],"") -> 71856 | G13: =IFERROR(PROPER(TRIM(tblCustomers[[#This Row],[Occupation]])),"") -> Entrepreneur | H13: =IFERROR(tblCustomers[[#This Row],[JoinDate]],"") -> 45501 | I13: =IFERROR(PROPER(TRIM(tblCustomers[[#This Row],[PurchaseChannel]])),"") -> Online | J13: =IFERROR(PROPER(TRIM(tblCustomers[[#This Row],[CustomerType]])),"") -> New | K13: =IFERROR(PROPER(TRIM(tblCustomers[[#This Row],[EngagementLevel]])),"") -> Medium | L13: =IFERROR(PROPER(TRIM(tblCustomers[[#This Row],[DiscountSensitivity]])),"") -> Medium | M13: =IFERROR(tblCustomers[[#This Row],[LastPurchaseDate]],"") -> 46059 | N13: =IFERROR(IF(tblCustomers[[#This Row],[Age]]<25,"<25",IF(tblCustomers[[#This Row],[Age]]<40,"25-39",IF(tblCustomers[[#This Row],[Age]]<55,"40-54","55+"))),"N/A") -> 55+ | O13: =IFERROR(IF(tblCustomers[[#This Row],[IncomeRange]]<25000,"Low",IF(tblCustomers[[#This Row],[IncomeRange]]<75000,"Mid","High")),"N/A") -> Mid | P13: =IFERROR(TEXT(tblCustomers[[#This Row],[JoinDate]],"DDDD"),"") -> Sunday | Q13: =IFERROR(IF(WEEKDAY(tblCustomers[[#This Row],[JoinDate]],2)>=6,TRUE(),FALSE()),FALSE()) -> TRUE | R13: =IFERROR(DATEDIF(tblCustomers[[#This Row],[JoinDate]],TODAY(),"M"),0) -> 20 | S13: =IFERROR(IF(AND(tblCustomers[[#This Row],[Age]]>=18,tblCustomers[[#This Row],[IncomeRange]]>0,tblCustomers[[#This Row],[CustomerID]]<>""),"OK","CHECK"),"CHECK") -> OK
A14: =IFERROR(TRIM(tblCustomers[[#This Row],[CustomerID]]),"") -> C0012 | B14: =IFERROR(PROPER(TRIM(tblCustomers[[#This Row],[Name]])),"") -> Gaurav Saxena | C14: =IFERROR(PROPER(TRIM(tblCustomers[[#This Row],[Gender]])),"") -> Male | D14: =IFERROR(tblCustomers[[#This Row],[Age]],"") -> 56 | E14: =IFERROR(PROPER(TRIM(tblCustomers[[#This Row],[City/Region]])),"") -> Lucknow | F14: =IFERROR(tblCustomers[[#This Row],[IncomeRange]],"") -> 137679 | G14: =IFERROR(PROPER(TRIM(tblCustomers[[#This Row],[Occupation]])),"") -> Retail Manager | H14: =IFERROR(tblCustomers[[#This Row],[JoinDate]],"") -> 45379 | I14: =IFERROR(PROPER(TRIM(tblCustomers[[#This Row],[PurchaseChannel]])),"") -> Online | J14: =IFERROR(PROPER(TRIM(tblCustomers[[#This Row],[CustomerType]])),"") -> Returning | K14: =IFERROR(PROPER(TRIM(tblCustomers[[#This Row],[EngagementLevel]])),"") -> Low | L14: =IFERROR(PROPER(TRIM(tblCustomers[[#This Row],[DiscountSensitivity]])),"") -> Medium | M14: =IFERROR(tblCustomers[[#This Row],[LastPurchaseDate]],"") -> 45965 | N14: =IFERROR(IF(tblCustomers[[#This Row],[Age]]<25,"<25",IF(tblCustomers[[#This Row],[Age]]<40,"25-39",IF(tblCustomers[[#This Row],[Age]]<55,"40-54","55+"))),"N/A") -> 55+ | O14: =IFERROR(IF(tblCustomers[[#This Row],[IncomeRange]]<25000,"Low",IF(tblCustomers[[#This Row],[IncomeRange]]<75000,"Mid","High")),"N/A") -> High | P14: =IFERROR(TEXT(tblCustomers[[#This Row],[JoinDate]],"DDDD"),"") -> Thursday | Q14: =IFERROR(IF(WEEKDAY(tblCustomers[[#This Row],[JoinDate]],2)>=6,TRUE(),FALSE()),FALSE()) -> FALSE | R14: =IFERROR(DATEDIF(tblCustomers[[#This Row],[JoinDate]],TODAY(),"M"),0) -> 24 | S14: =IFERROR(IF(AND(tblCustomers[[#This Row],[Age]]>=18,tblCustomers[[#This Row],[IncomeRange]]>0,tblCustomers[[#This Row],[CustomerID]]<>""),"OK","CHECK"),"CHECK") -> OK
... A202: =IFERROR(TRIM(tblCustomers[[#This Row],[CustomerID]]),"") -> C0200 | B202: =IFERROR(PROPER(TRIM(tblCustomers[[#This Row],[Name]])),"") -> Manoj Pillai | C202: =IFERROR(PROPER(TRIM(tblCustomers[[#This Row],[Gender]])),"") -> Male | D202: =IFERROR(tblCustomers[[#This Row],[Age]],"") -> 35 | E202: =IFERROR(PROPER(TRIM(tblCustomers[[#This Row],[City/Region]])),"") -> Lucknow | F202: =IFERROR(tblCustomers[[#This Row],[IncomeRange]],"") -> 73373 | G202: =IFERROR(PROPER(TRIM(tblCustomers[[#This Row],[Occupation]])),"") -> Consultant | H202: =IFERROR(tblCustomers[[#This Row],[JoinDate]],"") -> 45578 | I202: =IFERROR(PROPER(TRIM(tblCustomers[[#This Row],[PurchaseChannel]])),"") -> Offline | J202: =IFERROR(PROPER(TRIM(tblCustomers[[#This Row],[CustomerType]])),"") -> Returning | K202: =IFERROR(PROPER(TRIM(tblCustomers[[#This Row],[EngagementLevel]])),"") -> Medium | L202: =IFERROR(PROPER(TRIM(tblCustomers[[#This Row],[DiscountSensitivity]])),"") -> Low | M202: =IFERROR(tblCustomers[[#This Row],[LastPurchaseDate]],"") -> 45751 | N202: =IFERROR(IF(tblCustomers[[#This Row],[Age]]<25,"<25",IF(tblCustomers[[#This Row],[Age]]<40,"25-39",IF(tblCustomers[[#This Row],[Age]]<55,"40-54","55+"))),"N/A") -> 25-39 | O202: =IFERROR(IF(tblCustomers[[#This Row],[IncomeRange]]<25000,"Low",IF(tblCustomers[[#This Row],[IncomeRange]]<75000,"Mid","High")),"N/A") -> Mid | P202: =IFERROR(TEXT(tblCustomers[[#This Row],[JoinDate]],"DDDD"),"") -> Sunday | Q202: =IFERROR(IF(WEEKDAY(tblCustomers[[#This Row],[JoinDate]],2)>=6,TRUE(),FALSE()),FALSE()) -> TRUE | R202: =IFERROR(DATEDIF(tblCustomers[[#This Row],[JoinDate]],TODAY(),"M"),0) -> 18 | S202: =IFERROR(IF(AND(tblCustomers[[#This Row],[Age]]>=18,tblCustomers[[#This Row],[IncomeRange]]>0,tblCustomers[[#This Row],[CustomerID]]<>""),"OK","CHECK"),"CHECK") -> OK

Sheet Segmentation Logic
A1: 🔍 tblRFM — RFM Analysis + Survey Merge + Segment Assignment (Formula-Driven)
A2: CustomerID | B2: Name | C2: City/Region | D2: CustomerType | E2: EngagementLevel | F2: RFM_Recency | G2: RFM_Frequency | H2: RFM_Monetary | I2: R_Score | J2: F_Score | K2: M_Score | L2: RFM_Score | M2: Satisfaction | N2: RecommendationLikelihood | O2: SatisfactionIndex | P2: AgeGroup | Q2: IncomeBracket | R2: EngagementFlag | S2: ValueFlag | T2: CustomerSegment | U2: ProductPreference
A3: =IFERROR(tblClean[[#This Row],[CustomerID]],"") -> C0001 | B3: =IFERROR(tblClean[[#This Row],[Name (Cleaned)]],"") -> Arjun Sharma | C3: =IFERROR(tblClean[[#This Row],[City/Region (Cleaned)]],"") -> Noida | D3: =IFERROR(tblClean[[#This Row],[CustomerType]],"") -> New | E3: =IFERROR(tblClean[[#This Row],[EngagementLevel]],"") -> Low | F3: =IFERROR(TODAY()-'Raw Data'!M3,999) -> 40 | G3: =IFERROR(COUNTIFS(tblTransactions[CustomerID],A3),0) -> 1 | H3: =IFERROR(SUMIFS(tblTransactions[Amount (INR)],tblTransactions[CustomerID],A3),0) -> 10900 | I3: =IFERROR(IF(F3<=30,5,IF(F3<=60,4,IF(F3<=90,3,IF(F3<=180,2,1)))),1) -> 4 | J3: =IFERROR(IF(G3>=8,5,IF(G3>=6,4,IF(G3>=4,3,IF(G3>=2,2,1)))),1) -> 1 | K3: =IFERROR(IF(H3>=50000,5,IF(H3>=30000,4,IF(H3>=15000,3,IF(H3>=5000,2,1)))),1) -> 2 | L3: =IFERROR(TEXT(I3,"0")&TEXT(J3,"0")&TEXT(K3,"0"),"") -> 412 | M3: =IFERROR(INDEX('Raw Data'!$X$3:$X$202,MATCH(A3,'Raw Data'!$W$3:$W$202,0)),"") -> 4 | N3: =IFERROR(INDEX('Raw Data'!$Z$3:$Z$202,MATCH(A3,'Raw Data'!$W$3:$W$202,0)),"") -> 8 | O3: =IFERROR((IF(ISNUMBER(M3),M3,0)+IF(ISNUMBER(N3),N3/2,0))/MAX(1,(IF(ISNUMBER(M3),1,0)+IF(ISNUMBER(N3),1,0))),"") -> 4 | P3: =IFERROR(tblClean[[#This Row],[AgeGroup]],"") -> 55+ | Q3: =IFERROR(tblClean[[#This Row],[IncomeBracket]],"") -> Low | R3: =IFERROR(IF(E3="Low","LOW",IF(E3="Medium","MED","HIGH")),"N/A") -> LOW | S3: =IFERROR(IF(H3>=50000,"Premium",IF(H3>=15000,"Standard","Budget")),"N/A") -> Budget | T3: =IFERROR(IF(L3="555","Loyal",IF(AND(ISNUMBER(O3),O3>=4.5,G3>=3),"Loyal",IF(H3>=50000,"High Value",IF(AND(F3>90,G3<3),"At Risk",IF(AND(H3<30000,G3>=5),"Bargain Seeker","General"))))),"General") -> General | U3: =IFERROR(INDEX(tblTransactions[ProductCategory],MATCH(A3,tblTransactions[CustomerID],0)),"N/A") -> Beauty
A4: =IFERROR(tblClean[[#This Row],[CustomerID]],"") -> C0002 | B4: =IFERROR(tblClean[[#This Row],[Name (Cleaned)]],"") -> Vikram Singh | C4: =IFERROR(tblClean[[#This Row],[City/Region (Cleaned)]],"") -> Bangalore | D4: =IFERROR(tblClean[[#This Row],[CustomerType]],"") -> New | E4: =IFERROR(tblClean[[#This Row],[EngagementLevel]],"") -> Medium | F4: =IFERROR(TODAY()-'Raw Data'!M4,999) -> 82 | G4: =IFERROR(COUNTIFS(tblTransactions[CustomerID],A4),0) -> 1 | H4: =IFERROR(SUMIFS(tblTransactions[Amount (INR)],tblTransactions[CustomerID],A4),0) -> 3780 | I4: =IFERROR(IF(F4<=30,5,IF(F4<=60,4,IF(F4<=90,3,IF(F4<=180,2,1)))),1) -> 3 | J4: =IFERROR(IF(G4>=8,5,IF(G4>=6,4,IF(G4>=4,3,IF(G4>=2,2,1)))),1) -> 1 | K4: =IFERROR(IF(H4>=50000,5,IF(H4>=30000,4,IF(H4>=15000,3,IF(H4>=5000,2,1)))),1) -> 1 | L4: =IFERROR(TEXT(I4,"0")&TEXT(J4,"0")&TEXT(K4,"0"),"") -> 311 | M4: =IFERROR(INDEX('Raw Data'!$X$3:$X$202,MATCH(A4,'Raw Data'!$W$3:$W$202,0)),"") -> 3 | N4: =IFERROR(INDEX('Raw Data'!$Z$3:$Z$202,MATCH(A4,'Raw Data'!$W$3:$W$202,0)),"") -> 6 | O4: =IFERROR((IF(ISNUMBER(M4),M4,0)+IF(ISNUMBER(N4),N4/2,0))/MAX(1,(IF(ISNUMBER(M4),1,0)+IF(ISNUMBER(N4),1,0))),"") -> 3 | P4: =IFERROR(tblClean[[#This Row],[AgeGroup]],"") -> 40-54 | Q4: =IFERROR(tblClean[[#This Row],[IncomeBracket]],"") -> High | R4: =IFERROR(IF(E4="Low","LOW",IF(E4="Medium","MED","HIGH")),"N/A") -> MED | S4: =IFERROR(IF(H4>=50000,"Premium",IF(H4>=15000,"Standard","Budget")),"N/A") -> Budget | T4: =IFERROR(IF(L4="555","Loyal",IF(AND(ISNUMBER(O4),O4>=4.5,G4>=3),"Loyal",IF(H4>=50000,"High Value",IF(AND(F4>90,G4<3),"At Risk",IF(AND(H4<30000,G4>=5),"Bargain Seeker","General"))))),"General") -> General | U4: =IFERROR(INDEX(tblTransactions[ProductCategory],MATCH(A4,tblTransactions[CustomerID],0)),"N/A") -> Grocery
A5: =IFERROR(tblClean[[#This Row],[CustomerID]],"") -> C0003 | B5: =IFERROR(tblClean[[#This Row],[Name (Cleaned)]],"") -> Rohan Mehta | C5: =IFERROR(tblClean[[#This Row],[City/Region (Cleaned)]],"") -> Indore | D5: =IFERROR(tblClean[[#This Row],[CustomerType]],"") -> Returning | E5: =IFERROR(tblClean[[#This Row],[EngagementLevel]],"") -> Low | F5: =IFERROR(TODAY()-'Raw Data'!M5,999) -> 172 | G5: =IFERROR(COUNTIFS(tblTransactions[CustomerID],A5),0) -> 2 | H5: =IFERROR(SUMIFS(tblTransactions[Amount (INR)],tblTransactions[CustomerID],A5),0) -> 5380 | I5: =IFERROR(IF(F5<=30,5,IF(F5<=60,4,IF(F5<=90,3,IF(F5<=180,2,1)))),1) -> 2 | J5: =IFERROR(IF(G5>=8,5,IF(G5>=6,4,IF(G5>=4,3,IF(G5>=2,2,1)))),1) -> 2 | K5: =IFERROR(IF(H5>=50000,5,IF(H5>=30000,4,IF(H5>=15000,3,IF(H5>=5000,2,1)))),1) -> 2 | L5: =IFERROR(TEXT(I5,"0")&TEXT(J5,"0")&TEXT(K5,"0"),"") -> 222 | M5: =IFERROR(INDEX('Raw Data'!$X$3:$X$202,MATCH(A5,'Raw Data'!$W$3:$W$202,0)),"") -> 4 | N5: =IFERROR(INDEX('Raw Data'!$Z$3:$Z$202,MATCH(A5,'Raw Data'!$W$3:$W$202,0)),"") -> 7 | O5: =IFERROR((IF(ISNUMBER(M5),M5,0)+IF(ISNUMBER(N5),N5/2,0))/MAX(1,(IF(ISNUMBER(M5),1,0)+IF(ISNUMBER(N5),1,0))),"") -> 3.75 | P5: =IFERROR(tblClean[[#This Row],[AgeGroup]],"") -> 25-39 | Q5: =IFERROR(tblClean[[#This Row],[IncomeBracket]],"") -> Mid | R5: =IFERROR(IF(E5="Low","LOW",IF(E5="Medium","MED","HIGH")),"N/A") -> LOW | S5: =IFERROR(IF(H5>=50000,"Premium",IF(H5>=15000,"Standard","Budget")),"N/A") -> Budget | T5: =IFERROR(IF(L5="555","Loyal",IF(AND(ISNUMBER(O5),O5>=4.5,G5>=3),"Loyal",IF(H5>=50000,"High Value",IF(AND(F5>90,G5<3),"At Risk",IF(AND(H5<30000,G5>=5),"Bargain Seeker","General"))))),"General") -> At Risk | U5: =IFERROR(INDEX(tblTransactions[ProductCategory],MATCH(A5,tblTransactions[CustomerID],0)),"N/A") -> Grocery
A6: =IFERROR(tblClean[[#This Row],[CustomerID]],"") -> C0004 | B6: =IFERROR(tblClean[[#This Row],[Name (Cleaned)]],"") -> Nikhil Gupta | C6: =IFERROR(tblClean[[#This Row],[City/Region (Cleaned)]],"") -> Jaipur | D6: =IFERROR(tblClean[[#This Row],[CustomerType]],"") -> New | E6: =IFERROR(tblClean[[#This Row],[EngagementLevel]],"") -> Low | F6: =IFERROR(TODAY()-'Raw Data'!M6,999) -> 51 | G6: =IFERROR(COUNTIFS(tblTransactions[CustomerID],A6),0) -> 1 | H6: =IFERROR(SUMIFS(tblTransactions[Amount (INR)],tblTransactions[CustomerID],A6),0) -> 12070 | I6: =IFERROR(IF(F6<=30,5,IF(F6<=60,4,IF(F6<=90,3,IF(F6<=180,2,1)))),1) -> 4 | J6: =IFERROR(IF(G6>=8,5,IF(G6>=6,4,IF(G6>=4,3,IF(G6>=2,2,1)))),1) -> 1 | K6: =IFERROR(IF(H6>=50000,5,IF(H6>=30000,4,IF(H6>=15000,3,IF(H6>=5000,2,1)))),1) -> 2 | L6: =IFERROR(TEXT(I6,"0")&TEXT(J6,"0")&TEXT(K6,"0"),"") -> 412 | M6: =IFERROR(INDEX('Raw Data'!$X$3:$X$202,MATCH(A6,'Raw Data'!$W$3:$W$202,0)),"") -> 3 | N6: =IFERROR(INDEX('Raw Data'!$Z$3:$Z$202,MATCH(A6,'Raw Data'!$W$3:$W$202,0)),"") -> 6 | O6: =IFERROR((IF(ISNUMBER(M6),M6,0)+IF(ISNUMBER(N6),N6/2,0))/MAX(1,(IF(ISNUMBER(M6),1,0)+IF(ISNUMBER(N6),1,0))),"") -> 3 | P6: =IFERROR(tblClean[[#This Row],[AgeGroup]],"") -> 40-54 | Q6: =IFERROR(tblClean[[#This Row],[IncomeBracket]],"") -> Mid | R6: =IFERROR(IF(E6="Low","LOW",IF(E6="Medium","MED","HIGH")),"N/A") -> LOW | S6: =IFERROR(IF(H6>=50000,"Premium",IF(H6>=15000,"Standard","Budget")),"N/A") -> Budget | T6: =IFERROR(IF(L6="555","Loyal",IF(AND(ISNUMBER(O6),O6>=4.5,G6>=3),"Loyal",IF(H6>=50000,"High Value",IF(AND(F6>90,G6<3),"At Risk",IF(AND(H6<30000,G6>=5),"Bargain Seeker","General"))))),"General") -> General | U6: =IFERROR(INDEX(tblTransactions[ProductCategory],MATCH(A6,tblTransactions[CustomerID],0)),"N/A") -> Electronics
A7: =IFERROR(tblClean[[#This Row],[CustomerID]],"") -> C0005 | B7: =IFERROR(tblClean[[#This Row],[Name (Cleaned)]],"") -> Amit Verma | C7: =IFERROR(tblClean[[#This Row],[City/Region (Cleaned)]],"") -> Bhubaneswar | D7: =IFERROR(tblClean[[#This Row],[CustomerType]],"") -> Returning | E7: =IFERROR(tblClean[[#This Row],[EngagementLevel]],"") -> High | F7: =IFERROR(TODAY()-'Raw Data'!M7,999) -> 112 | G7: =IFERROR(COUNTIFS(tblTransactions[CustomerID],A7),0) -> 14 | H7: =IFERROR(SUMIFS(tblTransactions[Amount (INR)],tblTransactions[CustomerID],A7),0) -> 66820 | I7: =IFERROR(IF(F7<=30,5,IF(F7<=60,4,IF(F7<=90,3,IF(F7<=180,2,1)))),1) -> 2 | J7: =IFERROR(IF(G7>=8,5,IF(G7>=6,4,IF(G7>=4,3,IF(G7>=2,2,1)))),1) -> 5 | K7: =IFERROR(IF(H7>=50000,5,IF(H7>=30000,4,IF(H7>=15000,3,IF(H7>=5000,2,1)))),1) -> 5 | L7: =IFERROR(TEXT(I7,"0")&TEXT(J7,"0")&TEXT(K7,"0"),"") -> 255 | M7: =IFERROR(INDEX('Raw Data'!$X$3:$X$202,MATCH(A7,'Raw Data'!$W$3:$W$202,0)),"") -> 4 | N7: =IFERROR(INDEX('Raw Data'!$Z$3:$Z$202,MATCH(A7,'Raw Data'!$W$3:$W$202,0)),"") -> 4 | O7: =IFERROR((IF(ISNUMBER(M7),M7,0)+IF(ISNUMBER(N7),N7/2,0))/MAX(1,(IF(ISNUMBER(M7),1,0)+IF(ISNUMBER(N7),1,0))),"") -> 3 | P7: =IFERROR(tblClean[[#This Row],[AgeGroup]],"") -> 40-54 | Q7: =IFERROR(tblClean[[#This Row],[IncomeBracket]],"") -> Mid | R7: =IFERROR(IF(E7="Low","LOW",IF(E7="Medium","MED","HIGH")),"N/A") -> HIGH | S7: =IFERROR(IF(H7>=50000,"Premium",IF(H7>=15000,"Standard","Budget")),"N/A") -> Premium | T7: =IFERROR(IF(L7="555","Loyal",IF(AND(ISNUMBER(O7),O7>=4.5,G7>=3),"Loyal",IF(H7>=50000,"High Value",IF(AND(F7>90,G7<3),"At Risk",IF(AND(H7<30000,G7>=5),"Bargain Seeker","General"))))),"General") -> High Value | U7: =IFERROR(INDEX(tblTransactions[ProductCategory],MATCH(A7,tblTransactions[CustomerID],0)),"N/A") -> Home Decor
A8: =IFERROR(tblClean[[#This Row],[CustomerID]],"") -> C0006 | B8: =IFERROR(tblClean[[#This Row],[Name (Cleaned)]],"") -> Suresh Kumar | C8: =IFERROR(tblClean[[#This Row],[City/Region (Cleaned)]],"") -> Kolkata | D8: =IFERROR(tblClean[[#This Row],[CustomerType]],"") -> Returning | E8: =IFERROR(tblClean[[#This Row],[EngagementLevel]],"") -> Low | F8: =IFERROR(TODAY()-'Raw Data'!M8,999) -> 165 | G8: =IFERROR(COUNTIFS(tblTransactions[CustomerID],A8),0) -> 1 | H8: =IFERROR(SUMIFS(tblTransactions[Amount (INR)],tblTransactions[CustomerID],A8),0) -> 12330 | I8: =IFERROR(IF(F8<=30,5,IF(F8<=60,4,IF(F8<=90,3,IF(F8<=180,2,1)))),1) -> 2 | J8: =IFERROR(IF(G8>=8,5,IF(G8>=6,4,IF(G8>=4,3,IF(G8>=2,2,1)))),1) -> 1 | K8: =IFERROR(IF(H8>=50000,5,IF(H8>=30000,4,IF(H8>=15000,3,IF(H8>=5000,2,1)))),1) -> 2 | L8: =IFERROR(TEXT(I8,"0")&TEXT(J8,"0")&TEXT(K8,"0"),"") -> 212 | M8: =IFERROR(INDEX('Raw Data'!$X$3:$X$202,MATCH(A8,'Raw Data'!$W$3:$W$202,0)),"") -> 4 | N8: =IFERROR(INDEX('Raw Data'!$Z$3:$Z$202,MATCH(A8,'Raw Data'!$W$3:$W$202,0)),"") -> 7 | O8: =IFERROR((IF(ISNUMBER(M8),M8,0)+IF(ISNUMBER(N8),N8/2,0))/MAX(1,(IF(ISNUMBER(M8),1,0)+IF(ISNUMBER(N8),1,0))),"") -> 3.75 | P8: =IFERROR(tblClean[[#This Row],[AgeGroup]],"") -> 40-54 | Q8: =IFERROR(tblClean[[#This Row],[IncomeBracket]],"") -> High | R8: =IFERROR(IF(E8="Low","LOW",IF(E8="Medium","MED","HIGH")),"N/A") -> LOW | S8: =IFERROR(IF(H8>=50000,"Premium",IF(H8>=15000,"Standard","Budget")),"N/A") -> Budget | T8: =IFERROR(IF(L8="555","Loyal",IF(AND(ISNUMBER(O8),O8>=4.5,G8>=3),"Loyal",IF(H8>=50000,"High Value",IF(AND(F8>90,G8<3),"At Risk",IF(AND(H8<30000,G8>=5),"Bargain Seeker","General"))))),"General") -> At Risk | U8: =IFERROR(INDEX(tblTransactions[ProductCategory],MATCH(A8,tblTransactions[CustomerID],0)),"N/A") -> Grocery
A9: =IFERROR(tblClean[[#This Row],[CustomerID]],"") -> C0007 | B9: =IFERROR(tblClean[[#This Row],[Name (Cleaned)]],"") -> Rajesh Patel | C9: =IFERROR(tblClean[[#This Row],[City/Region (Cleaned)]],"") -> Bangalore | D9: =IFERROR(tblClean[[#This Row],[CustomerType]],"") -> Returning | E9: =IFERROR(tblClean[[#This Row],[EngagementLevel]],"") -> High | F9: =IFERROR(TODAY()-'Raw Data'!M9,999) -> 225 | G9: =IFERROR(COUNTIFS(tblTransactions[CustomerID],A9),0) -> 14 | H9: =IFERROR(SUMIFS(tblTransactions[Amount (INR)],tblTransactions[CustomerID],A9),0) -> 108600 | I9: =IFERROR(IF(F9<=30,5,IF(F9<=60,4,IF(F9<=90,3,IF(F9<=180,2,1)))),1) -> 1 | J9: =IFERROR(IF(G9>=8,5,IF(G9>=6,4,IF(G9>=4,3,IF(G9>=2,2,1)))),1) -> 5 | K9: =IFERROR(IF(H9>=50000,5,IF(H9>=30000,4,IF(H9>=15000,3,IF(H9>=5000,2,1)))),1) -> 5 | L9: =IFERROR(TEXT(I9,"0")&TEXT(J9,"0")&TEXT(K9,"0"),"") -> 155 | M9: =IFERROR(INDEX('Raw Data'!$X$3:$X$202,MATCH(A9,'Raw Data'!$W$3:$W$202,0)),"") -> 4 | N9: =IFERROR(INDEX('Raw Data'!$Z$3:$Z$202,MATCH(A9,'Raw Data'!$W$3:$W$202,0)),"") -> 4 | O9: =IFERROR((IF(ISNUMBER(M9),M9,0)+IF(ISNUMBER(N9),N9/2,0))/MAX(1,(IF(ISNUMBER(M9),1,0)+IF(ISNUMBER(N9),1,0))),"") -> 3 | P9: =IFERROR(tblClean[[#This Row],[AgeGroup]],"") -> 25-39 | Q9: =IFERROR(tblClean[[#This Row],[IncomeBracket]],"") -> High | R9: =IFERROR(IF(E9="Low","LOW",IF(E9="Medium","MED","HIGH")),"N/A") -> HIGH | S9: =IFERROR(IF(H9>=50000,"Premium",IF(H9>=15000,"Standard","Budget")),"N/A") -> Premium | T9: =IFERROR(IF(L9="555","Loyal",IF(AND(ISNUMBER(O9),O9>=4.5,G9>=3),"Loyal",IF(H9>=50000,"High Value",IF(AND(F9>90,G9<3),"At Risk",IF(AND(H9<30000,G9>=5),"Bargain Seeker","General"))))),"General") -> High Value | U9: =IFERROR(INDEX(tblTransactions[ProductCategory],MATCH(A9,tblTransactions[CustomerID],0)),"N/A") -> Clothing
A10: =IFERROR(tblClean[[#This Row],[CustomerID]],"") -> C0008 | B10: =IFERROR(tblClean[[#This Row],[Name (Cleaned)]],"") -> Aditya Joshi | C10: =IFERROR(tblClean[[#This Row],[City/Region (Cleaned)]],"") -> Hyderabad | D10: =IFERROR(tblClean[[#This Row],[CustomerType]],"") -> New | E10: =IFERROR(tblClean[[#This Row],[EngagementLevel]],"") -> Medium | F10: =IFERROR(TODAY()-'Raw Data'!M10,999) -> 93 | G10: =IFERROR(COUNTIFS(tblTransactions[CustomerID],A10),0) -> 1 | H10: =IFERROR(SUMIFS(tblTransactions[Amount (INR)],tblTransactions[CustomerID],A10),0) -> 570 | I10: =IFERROR(IF(F10<=30,5,IF(F10<=60,4,IF(F10<=90,3,IF(F10<=180,2,1)))),1) -> 2 | J10: =IFERROR(IF(G10>=8,5,IF(G10>=6,4,IF(G10>=4,3,IF(G10>=2,2,1)))),1) -> 1 | K10: =IFERROR(IF(H10>=50000,5,IF(H10>=30000,4,IF(H10>=15000,3,IF(H10>=5000,2,1)))),1) -> 1 | L10: =IFERROR(TEXT(I10,"0")&TEXT(J10,"0")&TEXT(K10,"0"),"") -> 211 | M10: =IFERROR(INDEX('Raw Data'!$X$3:$X$202,MATCH(A10,'Raw Data'!$W$3:$W$202,0)),"") -> 1 | N10: =IFERROR(INDEX('Raw Data'!$Z$3:$Z$202,MATCH(A10,'Raw Data'!$W$3:$W$202,0)),"") -> 5 | O10: =IFERROR((IF(ISNUMBER(M10),M10,0)+IF(ISNUMBER(N10),N10/2,0))/MAX(1,(IF(ISNUMBER(M10),1,0)+IF(ISNUMBER(N10),1,0))),"") -> 1.75 | P10: =IFERROR(tblClean[[#This Row],[AgeGroup]],"") -> 40-54 | Q10: =IFERROR(tblClean[[#This Row],[IncomeBracket]],"") -> High | R10: =IFERROR(IF(E10="Low","LOW",IF(E10="Medium","MED","HIGH")),"N/A") -> MED | S10: =IFERROR(IF(H10>=50000,"Premium",IF(H10>=15000,"Standard","Budget")),"N/A") -> Budget | T10: =IFERROR(IF(L10="555","Loyal",IF(AND(ISNUMBER(O10),O10>=4.5,G10>=3),"Loyal",IF(H10>=50000,"High Value",IF(AND(F10>90,G10<3),"At Risk",IF(AND(H10<30000,G10>=5),"Bargain Seeker","General"))))),"General") -> At Risk | U10: =IFERROR(INDEX(tblTransactions[ProductCategory],MATCH(A10,tblTransactions[CustomerID],0)),"N/A") -> Grocery
A11: =IFERROR(tblClean[[#This Row],[CustomerID]],"") -> C0009 | B11: =IFERROR(tblClean[[#This Row],[Name (Cleaned)]],"") -> Karan Kapoor | C11: =IFERROR(tblClean[[#This Row],[City/Region (Cleaned)]],"") -> Ahmedabad | D11: =IFERROR(tblClean[[#This Row],[CustomerType]],"") -> New | E11: =IFERROR(tblClean[[#This Row],[EngagementLevel]],"") -> High | F11: =IFERROR(TODAY()-'Raw Data'!M11,999) -> 92 | G11: =IFERROR(COUNTIFS(tblTransactions[CustomerID],A11),0) -> 1 | H11: =IFERROR(SUMIFS(tblTransactions[Amount (INR)],tblTransactions[CustomerID],A11),0) -> 6730 | I11: =IFERROR(IF(F11<=30,5,IF(F11<=60,4,IF(F11<=90,3,IF(F11<=180,2,1)))),1) -> 2 | J11: =IFERROR(IF(G11>=8,5,IF(G11>=6,4,IF(G11>=4,3,IF(G11>=2,2,1)))),1) -> 1 | K11: =IFERROR(IF(H11>=50000,5,IF(H11>=30000,4,IF(H11>=15000,3,IF(H11>=5000,2,1)))),1) -> 2 | L11: =IFERROR(TEXT(I11,"0")&TEXT(J11,"0")&TEXT(K11,"0"),"") -> 212 | M11: =IFERROR(INDEX('Raw Data'!$X$3:$X$202,MATCH(A11,'Raw Data'!$W$3:$W$202,0)),"") -> 4 | N11: =IFERROR(INDEX('Raw Data'!$Z$3:$Z$202,MATCH(A11,'Raw Data'!$W$3:$W$202,0)),"") -> 9 | O11: =IFERROR((IF(ISNUMBER(M11),M11,0)+IF(ISNUMBER(N11),N11/2,0))/MAX(1,(IF(ISNUMBER(M11),1,0)+IF(ISNUMBER(N11),1,0))),"") -> 4.25 | P11: =IFERROR(tblClean[[#This Row],[AgeGroup]],"") -> 40-54 | Q11: =IFERROR(tblClean[[#This Row],[IncomeBracket]],"") -> High | R11: =IFERROR(IF(E11="Low","LOW",IF(E11="Medium","MED","HIGH")),"N/A") -> HIGH | S11: =IFERROR(IF(H11>=50000,"Premium",IF(H11>=15000,"Standard","Budget")),"N/A") -> Budget | T11: =IFERROR(IF(L11="555","Loyal",IF(AND(ISNUMBER(O11),O11>=4.5,G11>=3),"Loyal",IF(H11>=50000,"High Value",IF(AND(F11>90,G11<3),"At Risk",IF(AND(H11<30000,G11>=5),"Bargain Seeker","General"))))),"General") -> At Risk | U11: =IFERROR(INDEX(tblTransactions[ProductCategory],MATCH(A11,tblTransactions[CustomerID],0)),"N/A") -> Grocery
A12: =IFERROR(tblClean[[#This Row],[CustomerID]],"") -> C0010 | B12: =IFERROR(tblClean[[#This Row],[Name (Cleaned)]],"") -> Deepak Nair | C12: =IFERROR(tblClean[[#This Row],[City/Region (Cleaned)]],"") -> Jaipur | D12: =IFERROR(tblClean[[#This Row],[CustomerType]],"") -> Returning | E12: =IFERROR(tblClean[[#This Row],[EngagementLevel]],"") -> High | F12: =IFERROR(TODAY()-'Raw Data'!M12,999) -> 40 | G12: =IFERROR(COUNTIFS(tblTransactions[CustomerID],A12),0) -> 14 | H12: =IFERROR(SUMIFS(tblTransactions[Amount (INR)],tblTransactions[CustomerID],A12),0) -> 51230 | I12: =IFERROR(IF(F12<=30,5,IF(F12<=60,4,IF(F12<=90,3,IF(F12<=180,2,1)))),1) -> 4 | J12: =IFERROR(IF(G12>=8,5,IF(G12>=6,4,IF(G12>=4,3,IF(G12>=2,2,1)))),1) -> 5 | K12: =IFERROR(IF(H12>=50000,5,IF(H12>=30000,4,IF(H12>=15000,3,IF(H12>=5000,2,1)))),1) -> 5 | L12: =IFERROR(TEXT(I12,"0")&TEXT(J12,"0")&TEXT(K12,"0"),"") -> 455 | M12: =IFERROR(INDEX('Raw Data'!$X$3:$X$202,MATCH(A12,'Raw Data'!$W$3:$W$202,0)),"") -> 3 | N12: =IFERROR(INDEX('Raw Data'!$Z$3:$Z$202,MATCH(A12,'Raw Data'!$W$3:$W$202,0)),"") -> 6 | O12: =IFERROR((IF(ISNUMBER(M12),M12,0)+IF(ISNUMBER(N12),N12/2,0))/MAX(1,(IF(ISNUMBER(M12),1,0)+IF(ISNUMBER(N12),1,0))),"") -> 3 | P12: =IFERROR(tblClean[[#This Row],[AgeGroup]],"") -> <25 | Q12: =IFERROR(tblClean[[#This Row],[IncomeBracket]],"") -> Mid | R12: =IFERROR(IF(E12="Low","LOW",IF(E12="Medium","MED","HIGH")),"N/A") -> HIGH | S12: =IFERROR(IF(H12>=50000,"Premium",IF(H12>=15000,"Standard","Budget")),"N/A") -> Premium | T12: =IFERROR(IF(L12="555","Loyal",IF(AND(ISNUMBER(O12),O12>=4.5,G12>=3),"Loyal",IF(H12>=50000,"High Value",IF(AND(F12>90,G12<3),"At Risk",IF(AND(H12<30000,G12>=5),"Bargain Seeker","General"))))),"General") -> High Value | U12: =IFERROR(INDEX(tblTransactions[ProductCategory],MATCH(A12,tblTransactions[CustomerID],0)),"N/A") -> Sports
A13: =IFERROR(tblClean[[#This Row],[CustomerID]],"") -> C0011 | B13: =IFERROR(tblClean[[#This Row],[Name (Cleaned)]],"") -> Manish Tiwari | C13: =IFERROR(tblClean[[#This Row],[City/Region (Cleaned)]],"") -> Bhopal | D13: =IFERROR(tblClean[[#This Row],[CustomerType]],"") -> New | E13: =IFERROR(tblClean[[#This Row],[EngagementLevel]],"") -> Medium | F13: =IFERROR(TODAY()-'Raw Data'!M13,999) -> 66 | G13: =IFERROR(COUNTIFS(tblTransactions[CustomerID],A13),0) -> 1 | H13: =IFERROR(SUMIFS(tblTransactions[Amount (INR)],tblTransactions[CustomerID],A13),0) -> 3660 | I13: =IFERROR(IF(F13<=30,5,IF(F13<=60,4,IF(F13<=90,3,IF(F13<=180,2,1)))),1) -> 3 | J13: =IFERROR(IF(G13>=8,5,IF(G13>=6,4,IF(G13>=4,3,IF(G13>=2,2,1)))),1) -> 1 | K13: =IFERROR(IF(H13>=50000,5,IF(H13>=30000,4,IF(H13>=15000,3,IF(H13>=5000,2,1)))),1) -> 1 | L13: =IFERROR(TEXT(I13,"0")&TEXT(J13,"0")&TEXT(K13,"0"),"") -> 311 | M13: =IFERROR(INDEX('Raw Data'!$X$3:$X$202,MATCH(A13,'Raw Data'!$W$3:$W$202,0)),"") -> 4 | N13: =IFERROR(INDEX('Raw Data'!$Z$3:$Z$202,MATCH(A13,'Raw Data'!$W$3:$W$202,0)),"") -> 8 | O13: =IFERROR((IF(ISNUMBER(M13),M13,0)+IF(ISNUMBER(N13),N13/2,0))/MAX(1,(IF(ISNUMBER(M13),1,0)+IF(ISNUMBER(N13),1,0))),"") -> 4 | P13: =IFERROR(tblClean[[#This Row],[AgeGroup]],"") -> 55+ | Q13: =IFERROR(tblClean[[#This Row],[IncomeBracket]],"") -> Mid | R13: =IFERROR(IF(E13="Low","LOW",IF(E13="Medium","MED","HIGH")),"N/A") -> MED | S13: =IFERROR(IF(H13>=50000,"Premium",IF(H13>=15000,"Standard","Budget")),"N/A") -> Budget | T13: =IFERROR(IF(L13="555","Loyal",IF(AND(ISNUMBER(O13),O13>=4.5,G13>=3),"Loyal",IF(H13>=50000,"High Value",IF(AND(F13>90,G13<3),"At Risk",IF(AND(H13<30000,G13>=5),"Bargain Seeker","General"))))),"General") -> General | U13: =IFERROR(INDEX(tblTransactions[ProductCategory],MATCH(A13,tblTransactions[CustomerID],0)),"N/A") -> Beauty
A14: =IFERROR(tblClean[[#This Row],[CustomerID]],"") -> C0012 | B14: =IFERROR(tblClean[[#This Row],[Name (Cleaned)]],"") -> Gaurav Saxena | C14: =IFERROR(tblClean[[#This Row],[City/Region (Cleaned)]],"") -> Lucknow | D14: =IFERROR(tblClean[[#This Row],[CustomerType]],"") -> Returning | E14: =IFERROR(tblClean[[#This Row],[EngagementLevel]],"") -> Low | F14: =IFERROR(TODAY()-'Raw Data'!M14,999) -> 160 | G14: =IFERROR(COUNTIFS(tblTransactions[CustomerID],A14),0) -> 2 | H14: =IFERROR(SUMIFS(tblTransactions[Amount (INR)],tblTransactions[CustomerID],A14),0) -> 5290 | I14: =IFERROR(IF(F14<=30,5,IF(F14<=60,4,IF(F14<=90,3,IF(F14<=180,2,1)))),1) -> 2 | J14: =IFERROR(IF(G14>=8,5,IF(G14>=6,4,IF(G14>=4,3,IF(G14>=2,2,1)))),1) -> 2 | K14: =IFERROR(IF(H14>=50000,5,IF(H14>=30000,4,IF(H14>=15000,3,IF(H14>=5000,2,1)))),1) -> 2 | L14: =IFERROR(TEXT(I14,"0")&TEXT(J14,"0")&TEXT(K14,"0"),"") -> 222 | M14: =IFERROR(INDEX('Raw Data'!$X$3:$X$202,MATCH(A14,'Raw Data'!$W$3:$W$202,0)),"") -> 4 | N14: =IFERROR(INDEX('Raw Data'!$Z$3:$Z$202,MATCH(A14,'Raw Data'!$W$3:$W$202,0)),"") -> 8 | O14: =IFERROR((IF(ISNUMBER(M14),M14,0)+IF(ISNUMBER(N14),N14/2,0))/MAX(1,(IF(ISNUMBER(M14),1,0)+IF(ISNUMBER(N14),1,0))),"") -> 4 | P14: =IFERROR(tblClean[[#This Row],[AgeGroup]],"") -> 55+ | Q14: =IFERROR(tblClean[[#This Row],[IncomeBracket]],"") -> High | R14: =IFERROR(IF(E14="Low","LOW",IF(E14="Medium","MED","HIGH")),"N/A") -> LOW | S14: =IFERROR(IF(H14>=50000,"Premium",IF(H14>=15000,"Standard","Budget")),"N/A") -> Budget | T14: =IFERROR(IF(L14="555","Loyal",IF(AND(ISNUMBER(O14),O14>=4.5,G14>=3),"Loyal",IF(H14>=50000,"High Value",IF(AND(F14>90,G14<3),"At Risk",IF(AND(H14<30000,G14>=5),"Bargain Seeker","General"))))),"General") -> At Risk | U14: =IFERROR(INDEX(tblTransactions[ProductCategory],MATCH(A14,tblTransactions[CustomerID],0)),"N/A") -> Grocery
... A202: =IFERROR(tblClean[[#This Row],[CustomerID]],"") -> C0200 | B202: =IFERROR(tblClean[[#This Row],[Name (Cleaned)]],"") -> Manoj Pillai | C202: =IFERROR(tblClean[[#This Row],[City/Region (Cleaned)]],"") -> Lucknow | D202: =IFERROR(tblClean[[#This Row],[CustomerType]],"") -> Returning | E202: =IFERROR(tblClean[[#This Row],[EngagementLevel]],"") -> Medium | F202: =IFERROR(TODAY()-'Raw Data'!M202,999) -> 374 | G202: =IFERROR(COUNTIFS(tblTransactions[CustomerID],A202),0) -> 4 | H202: =IFERROR(SUMIFS(tblTransactions[Amount (INR)],tblTransactions[CustomerID],A202),0) -> 52070 | I202: =IFERROR(IF(F202<=30,5,IF(F202<=60,4,IF(F202<=90,3,IF(F202<=180,2,1)))),1) -> 1 | J202: =IFERROR(IF(G202>=8,5,IF(G202>=6,4,IF(G202>=4,3,IF(G202>=2,2,1)))),1) -> 3 | K202: =IFERROR(IF(H202>=50000,5,IF(H202>=30000,4,IF(H202>=15000,3,IF(H202>=5000,2,1)))),1) -> 5 | L202: =IFERROR(TEXT(I202,"0")&TEXT(J202,"0")&TEXT(K202,"0"),"") -> 135 | M202: =IFERROR(INDEX('Raw Data'!$X$3:$X$202,MATCH(A202,'Raw Data'!$W$3:$W$202,0)),"") -> 1 | N202: =IFERROR(INDEX('Raw Data'!$Z$3:$Z$202,MATCH(A202,'Raw Data'!$W$3:$W$202,0)),"") -> 10 | O202: =IFERROR((IF(ISNUMBER(M202),M202,0)+IF(ISNUMBER(N202),N202/2,0))/MAX(1,(IF(ISNUMBER(M202),1,0)+IF(ISNUMBER(N202),1,0))),"") -> 3 | P202: =IFERROR(tblClean[[#This Row],[AgeGroup]],"") -> 25-39 | Q202: =IFERROR(tblClean[[#This Row],[IncomeBracket]],"") -> Mid | R202: =IFERROR(IF(E202="Low","LOW",IF(E202="Medium","MED","HIGH")),"N/A") -> MED | S202: =IFERROR(IF(H202>=50000,"Premium",IF(H202>=15000,"Standard","Budget")),"N/A") -> Premium | T202: =IFERROR(IF(L202="555","Loyal",IF(AND(ISNUMBER(O202),O202>=4.5,G202>=3),"Loyal",IF(H202>=50000,"High Value",IF(AND(F202>90,G202<3),"At Risk",IF(AND(H202<30000,G202>=5),"Bargain Seeker","General"))))),"General") -> High Value | U202: =IFERROR(INDEX(tblTransactions[ProductCategory],MATCH(A202,tblTransactions[CustomerID],0)),"N/A") -> Grocery

Sheet KPI Summary
A1: 📊 MARKET RESEARCH & CUSTOMER SEGMENTATION — KPI SUMMARY | FY 2025–26
A2: 📊 Overview
A3: Total Customers | B3: =COUNTA(tblClean[CustomerID]) -> 200
A4: Total Transactions | B4: =COUNTA(tblTransactions[TransactionID]) -> 1044
A5: Date Range | B5: =TEXT(MIN(tblTransactions[Date]),"MMM YYYY")&" - "&TEXT(MAX(tblTransactions[Date]),"MMM YYYY") -> Apr 2025 - Mar 2026
A6: Financial Year | B6: FY 2025–26
A7: Product Categories | B7: {=ROUND(SUMPRODUCT(1/COUNTIF(tblTransactions[ProductCategory],tblTransactions[ProductCategory])),0)} -> 7
A8: Cities / Regions | B8: =SUMPRODUCT(1/COUNTIF(tblClean[City/Region (Cleaned)],tblClean[City/Region (Cleaned)])) -> 23
A10: 💰 Revenue KPIs
A11: Total Revenue (INR) | B11: =SUM(tblTransactions[Amount (INR)]) -> 10038773
A12: Average Order Value (AOV) | B12: =IFERROR(AVERAGE(tblTransactions[Amount (INR)]),0) -> 9615.683
A13: Online Revenue (INR) | B13: =IFERROR(SUMPRODUCT((tblClean[PurchaseChannel]="Online")*SUMIFS(tblTransactions[Amount (INR)],tblTransactions[CustomerID],tblClean[CustomerID])),0) -> 4736921
A14: Offline Revenue (INR) | B14: =IFERROR(SUMPRODUCT((tblClean[PurchaseChannel]="Offline")*SUMIFS(tblTransactions[Amount (INR)],tblTransactions[CustomerID],tblClean[CustomerID])),0) -> 5301852
A15: Online Revenue % | B15: =IFERROR(B13/B11,0) -> 0.47186255
A16: Offline Revenue % | B16: =IFERROR(B14/B11,0) -> 0.52813745
A17: Highest Single Transaction (INR) | B17: =MAX(tblTransactions[Amount (INR)]) -> 25000
A18: Median Order Value (INR) | B18: =MEDIAN(tblTransactions[Amount (INR)]) -> 7485
A20: 👥 Customer KPIs
A21: Total Customers | B21: =COUNTA(tblClean[CustomerID]) -> 200
A22: Active Customers (Last Purchase ≤90 days) | B22: =COUNTIFS(tblCustomers[LastPurchaseDate],">="&(TODAY()-90)) -> 78
A23: Returning / Repeat Customers | B23: =COUNTIFS(tblClean[CustomerType],"Returning") -> 115
A24: Repeat Customer % | B24: =IFERROR(COUNTIFS(tblClean[CustomerType],"Returning")/COUNTA(tblClean[CustomerID]),0) -> 0.575
A25: High Value Customers | B25: =COUNTIFS(tblRFM[CustomerSegment],"High Value") -> 74
A26: High Value % | B26: =IFERROR(COUNTIFS(tblRFM[CustomerSegment],"High Value")/COUNTA(tblClean[CustomerID]),0) -> 0.37
A27: Loyal Customers | B27: =COUNTIFS(tblRFM[CustomerSegment],"Loyal") -> 17
A28: Loyal % | B28: =IFERROR(COUNTIFS(tblRFM[CustomerSegment],"Loyal")/COUNTA(tblClean[CustomerID]),0) -> 0.085
A29: Avg Purchase Frequency (transactions/customer) | B29: =IFERROR(COUNTA(tblTransactions[TransactionID])/COUNTA(tblClean[CustomerID]),0) -> 5.22
A30: Customer Retention Indicator (Active+Returning/2) | B30: =IFERROR((COUNTIFS(tblRFM[RFM_Recency],"<=90")+COUNTIFS(tblClean[CustomerType],"Returning"))/2,0) -> 96.5
A32: ⚠️ Risk Summary
A33: At-Risk Customers | B33: =COUNTIFS(tblRFM[CustomerSegment],"At Risk") -> 38
A34: At-Risk % | B34: =IFERROR(COUNTIFS(tblRFM[CustomerSegment],"At Risk")/COUNTA(tblClean[CustomerID]),0) -> 0.19
A35: Low Engagement Count | B35: =COUNTIFS(tblClean[EngagementLevel],"Low") -> 57
A36: Low Engagement % | B36: =IFERROR(COUNTIFS(tblClean[EngagementLevel],"Low")/COUNTA(tblClean[CustomerID]),0) -> 0.285
A37: Bargain Seekers | B37: =COUNTIFS(tblRFM[CustomerSegment],"Bargain Seeker") -> 8
A39: 🔍 Satisfaction KPIs
A40: Avg Satisfaction Score (1-5) | B40: =IFERROR(AVERAGE(tblSurvey[Satisfaction]),0) -> 3.165
A41: Avg Recommendation Likelihood (1-10) | B41: =IFERROR(AVERAGE(tblSurvey[RecommendationLikelihood]),0) -> 6.415
A42: Avg Satisfaction Index | B42: =IFERROR(AVERAGEIF(tblRFM[SatisfactionIndex],">0"),0) -> 3.18625
A43: High Satisfaction (≥4) Count | B43: =COUNTIFS(tblSurvey[Satisfaction],">=4") -> 88
A45: 📋 Segment-wise Summary
A46: CustomerSegment | B46: Customer Count | C46: Total Revenue (INR) | D46: Revenue % | E46: Avg Spend/Customer
A47: Loyal | B47: =COUNTIFS(tblRFM[CustomerSegment],A47) -> 17 | C47: =IFERROR(SUMIFS(tblFinal[RFM_Monetary],tblFinal[CustomerSegment],A47),0) -> 1525892 | D47: =IFERROR(C47/SUM($C$47:$C$51),0) -> 0.15199985 | E47: =IFERROR(C47/B47,0) -> 89758.353
A48: High Value | B48: =COUNTIFS(tblRFM[CustomerSegment],A48) -> 74 | C48: =IFERROR(SUMIFS(tblFinal[RFM_Monetary],tblFinal[CustomerSegment],A48),0) -> 6607484 | D48: =IFERROR(C48/SUM($C$47:$C$51),0) -> 0.65819638 | E48: =IFERROR(C48/B48,0) -> 89290.324
A49: At Risk | B49: =COUNTIFS(tblRFM[CustomerSegment],A49) -> 38 | C49: =IFERROR(SUMIFS(tblFinal[RFM_Monetary],tblFinal[CustomerSegment],A49),0) -> 537567 | D49: =IFERROR(C49/SUM($C$47:$C$51),0) -> 0.053549074 | E49: =IFERROR(C49/B49,0) -> 14146.5
A50: Bargain Seeker | B50: =COUNTIFS(tblRFM[CustomerSegment],A50) -> 8 | C50: =IFERROR(SUMIFS(tblFinal[RFM_Monetary],tblFinal[CustomerSegment],A50),0) -> 184330 | D50: =IFERROR(C50/SUM($C$47:$C$51),0) -> 0.018361806 | E50: =IFERROR(C50/B50,0) -> 23041.25
A51: General | B51: =COUNTIFS(tblRFM[CustomerSegment],A51) -> 63 | C51: =IFERROR(SUMIFS(tblFinal[RFM_Monetary],tblFinal[CustomerSegment],A51),0) -> 1183500 | D51: =IFERROR(C51/SUM($C$47:$C$51),0) -> 0.11789289 | E51: =IFERROR(C51/B51,0) -> 18785.714
A53: 🗺️ Region-wise Revenue Summary
A54: City/Region | B54: Customer Count | C54: Total Revenue (INR) | D54: Avg Spend | E54: At-Risk Count
A55: Ahmedabad | B55: =COUNTIFS(tblClean[City/Region (Cleaned)],A55) -> 19 | C55: {=IFERROR(SUMPRODUCT((tblClean[City/Region (Cleaned)]=A55)*SUMIF(tblTransactions[CustomerID],tblClean[CustomerID],tblTransactions[Amount (INR)])),0)} -> 666456 | D55: =IFERROR(C55/B55,0) -> 35076.632 | E55: =IFERROR(COUNTIFS(tblClean[City/Region (Cleaned)],A55,tblRFM[CustomerSegment],"At Risk"),0) -> 5
A56: Bangalore | B56: =COUNTIFS(tblClean[City/Region (Cleaned)],A56) -> 14 | C56: {=IFERROR(SUMPRODUCT((tblClean[City/Region (Cleaned)]=A56)*SUMIF(tblTransactions[CustomerID],tblClean[CustomerID],tblTransactions[Amount (INR)])),0)} -> 792765 | D56: =IFERROR(C56/B56,0) -> 56626.071 | E56: =IFERROR(COUNTIFS(tblClean[City/Region (Cleaned)],A56,tblRFM[CustomerSegment],"At Risk"),0) -> 1
A57: Bhopal | B57: =COUNTIFS(tblClean[City/Region (Cleaned)],A57) -> 9 | C57: {=IFERROR(SUMPRODUCT((tblClean[City/Region (Cleaned)]=A57)*SUMIF(tblTransactions[CustomerID],tblClean[CustomerID],tblTransactions[Amount (INR)])),0)} -> 479969 | D57: =IFERROR(C57/B57,0) -> 53329.889 | E57: =IFERROR(COUNTIFS(tblClean[City/Region (Cleaned)],A57,tblRFM[CustomerSegment],"At Risk"),0) -> 1
A58: Bhubaneswar | B58: =COUNTIFS(tblClean[City/Region (Cleaned)],A58) -> 11 | C58: {=IFERROR(SUMPRODUCT((tblClean[City/Region (Cleaned)]=A58)*SUMIF(tblTransactions[CustomerID],tblClean[CustomerID],tblTransactions[Amount (INR)])),0)} -> 663318 | D58: =IFERROR(C58/B58,0) -> 60301.636 | E58: =IFERROR(COUNTIFS(tblClean[City/Region (Cleaned)],A58,tblRFM[CustomerSegment],"At Risk"),0) -> 3
A59: Chandigarh | B59: =COUNTIFS(tblClean[City/Region (Cleaned)],A59) -> 8 | C59: {=IFERROR(SUMPRODUCT((tblClean[City/Region (Cleaned)]=A59)*SUMIF(tblTransactions[CustomerID],tblClean[CustomerID],tblTransactions[Amount (INR)])),0)} -> 445218 | D59: =IFERROR(C59/B59,0) -> 55652.25 | E59: =IFERROR(COUNTIFS(tblClean[City/Region (Cleaned)],A59,tblRFM[CustomerSegment],"At Risk"),0) -> 0
A60: Chennai | B60: =COUNTIFS(tblClean[City/Region (Cleaned)],A60) -> 11 | C60: {=IFERROR(SUMPRODUCT((tblClean[City/Region (Cleaned)]=A60)*SUMIF(tblTransactions[CustomerID],tblClean[CustomerID],tblTransactions[Amount (INR)])),0)} -> 751340 | D60: =IFERROR(C60/B60,0) -> 68303.636 | E60: =IFERROR(COUNTIFS(tblClean[City/Region (Cleaned)],A60,tblRFM[CustomerSegment],"At Risk"),0) -> 1
A61: Coimbatore | B61: =COUNTIFS(tblClean[City/Region (Cleaned)],A61) -> 4 | C61: {=IFERROR(SUMPRODUCT((tblClean[City/Region (Cleaned)]=A61)*SUMIF(tblTransactions[CustomerID],tblClean[CustomerID],tblTransactions[Amount (INR)])),0)} -> 207197 | D61: =IFERROR(C61/B61,0) -> 51799.25 | E61: =IFERROR(COUNTIFS(tblClean[City/Region (Cleaned)],A61,tblRFM[CustomerSegment],"At Risk"),0) -> 1
A62: Delhi | B62: =COUNTIFS(tblClean[City/Region (Cleaned)],A62) -> 8 | C62: {=IFERROR(SUMPRODUCT((tblClean[City/Region (Cleaned)]=A62)*SUMIF(tblTransactions[CustomerID],tblClean[CustomerID],tblTransactions[Amount (INR)])),0)} -> 275789 | D62: =IFERROR(C62/B62,0) -> 34473.625 | E62: =IFERROR(COUNTIFS(tblClean[City/Region (Cleaned)],A62,tblRFM[CustomerSegment],"At Risk"),0) -> 1
A63: Hyderabad | B63: =COUNTIFS(tblClean[City/Region (Cleaned)],A63) -> 8 | C63: {=IFERROR(SUMPRODUCT((tblClean[City/Region (Cleaned)]=A63)*SUMIF(tblTransactions[CustomerID],tblClean[CustomerID],tblTransactions[Amount (INR)])),0)} -> 396008 | D63: =IFERROR(C63/B63,0) -> 49501 | E63: =IFERROR(COUNTIFS(tblClean[City/Region (Cleaned)],A63,tblRFM[CustomerSegment],"At Risk"),0) -> 3
A64: Indore | B64: =COUNTIFS(tblClean[City/Region (Cleaned)],A64) -> 9 | C64: {=IFERROR(SUMPRODUCT((tblClean[City/Region (Cleaned)]=A64)*SUMIF(tblTransactions[CustomerID],tblClean[CustomerID],tblTransactions[Amount (INR)])),0)} -> 405192 | D64: =IFERROR(C64/B64,0) -> 45021.333 | E64: =IFERROR(COUNTIFS(tblClean[City/Region (Cleaned)],A64,tblRFM[CustomerSegment],"At Risk"),0) -> 3
A65: Jaipur | B65: =COUNTIFS(tblClean[City/Region (Cleaned)],A65) -> 9 | C65: {=IFERROR(SUMPRODUCT((tblClean[City/Region (Cleaned)]=A65)*SUMIF(tblTransactions[CustomerID],tblClean[CustomerID],tblTransactions[Amount (INR)])),0)} -> 500839 | D65: =IFERROR(C65/B65,0) -> 55648.778 | E65: =IFERROR(COUNTIFS(tblClean[City/Region (Cleaned)],A65,tblRFM[CustomerSegment],"At Risk"),0) -> 1
A66: Kolkata | B66: =COUNTIFS(tblClean[City/Region (Cleaned)],A66) -> 6 | C66: {=IFERROR(SUMPRODUCT((tblClean[City/Region (Cleaned)]=A66)*SUMIF(tblTransactions[CustomerID],tblClean[CustomerID],tblTransactions[Amount (INR)])),0)} -> 216229 | D66: =IFERROR(C66/B66,0) -> 36038.167 | E66: =IFERROR(COUNTIFS(tblClean[City/Region (Cleaned)],A66,tblRFM[CustomerSegment],"At Risk"),0) -> 2
... A77: Kochi | B77: =COUNTIFS(tblClean[City/Region (Cleaned)],A77) -> 1 | C77: {=IFERROR(SUMPRODUCT((tblClean[City/Region (Cleaned)]=A77)*SUMIF(tblTransactions[CustomerID],tblClean[CustomerID],tblTransactions[Amount (INR)])),0)} -> 64690 | D77: =IFERROR(C77/B77,0) -> 64690 | E77: =IFERROR(COUNTIFS(tblClean[City/Region (Cleaned)],A77,tblRFM[CustomerSegment],"At Risk"),0) -> 0

Sheet Pivot Analysis
A1: 📊 tblFinal — Flat Pivot-Ready Dataset (Fully Formula-Driven | Zero Restructuring Required for Pivots) | V1: 📋 Summary Analysis Tables (Formula-Driven)
A2: CustomerID | B2: Name | C2: Gender | D2: AgeGroup | E2: City/Region | F2: IncomeBracket | G2: CustomerType | H2: EngagementLevel | I2: CustomerSegment | J2: ProductPreference | K2: PurchaseChannel | L2: RFM_Recency | M2: RFM_Frequency | N2: RFM_Monetary | O2: RFM_Score | P2: SatisfactionIndex | Q2: Satisfaction | R2: RecommendationLikelihood | S2: TotalTransactions | T2: DiscountSensitivity | V2: Table A — Segment-wise Summary
A3: =tblRFM[[#This Row],[CustomerID]] -> C0001 | B3: =tblRFM[[#This Row],[Name]] -> Arjun Sharma | C3: =IFERROR(INDEX(tblClean[Gender],MATCH(A3,tblClean[CustomerID],0)),"") -> Male | D3: =tblRFM[[#This Row],[AgeGroup]] -> 55+ | E3: =tblRFM[[#This Row],[City/Region]] -> Noida | F3: =tblRFM[[#This Row],[IncomeBracket]] -> Low | G3: =tblRFM[[#This Row],[CustomerType]] -> New | H3: =tblRFM[[#This Row],[EngagementLevel]] -> Low | I3: =tblRFM[[#This Row],[CustomerSegment]] -> General | J3: =tblRFM[[#This Row],[ProductPreference]] -> Beauty | K3: =IFERROR(INDEX(tblClean[PurchaseChannel],MATCH(A3,tblClean[CustomerID],0)),"") -> Online | L3: =tblRFM[[#This Row],[RFM_Recency]] -> 40 | M3: =tblRFM[[#This Row],[RFM_Frequency]] -> 1 | N3: =tblRFM[[#This Row],[RFM_Monetary]] -> 10900 | O3: =tblRFM[[#This Row],[RFM_Score]] -> 412 | P3: =IFERROR(tblRFM[[#This Row],[SatisfactionIndex]],"") -> 4 | Q3: =IFERROR(tblRFM[[#This Row],[Satisfaction]],"") -> 4 | R3: =IFERROR(tblRFM[[#This Row],[RecommendationLikelihood]],"") -> 8 | S3: =COUNTIFS(tblTransactions[CustomerID],A3) -> 1 | T3: =IFERROR(INDEX(tblClean[DiscountSensitivity],MATCH(A3,tblClean[CustomerID],0)),"") -> High | V3: Segment | W3: Count | X3: Total Revenue | Y3: Avg AOV | Z3: Avg Monetary | AA3: HV Count
A4: =tblRFM[[#This Row],[CustomerID]] -> C0002 | B4: =tblRFM[[#This Row],[Name]] -> Vikram Singh | C4: =IFERROR(INDEX(tblClean[Gender],MATCH(A4,tblClean[CustomerID],0)),"") -> Male | D4: =tblRFM[[#This Row],[AgeGroup]] -> 40-54 | E4: =tblRFM[[#This Row],[City/Region]] -> Bangalore | F4: =tblRFM[[#This Row],[IncomeBracket]] -> High | G4: =tblRFM[[#This Row],[CustomerType]] -> New | H4: =tblRFM[[#This Row],[EngagementLevel]] -> Medium | I4: =tblRFM[[#This Row],[CustomerSegment]] -> General | J4: =tblRFM[[#This Row],[ProductPreference]] -> Grocery | K4: =IFERROR(INDEX(tblClean[PurchaseChannel],MATCH(A4,tblClean[CustomerID],0)),"") -> Online | L4: =tblRFM[[#This Row],[RFM_Recency]] -> 82 | M4: =tblRFM[[#This Row],[RFM_Frequency]] -> 1 | N4: =tblRFM[[#This Row],[RFM_Monetary]] -> 3780 | O4: =tblRFM[[#This Row],[RFM_Score]] -> 311 | P4: =IFERROR(tblRFM[[#This Row],[SatisfactionIndex]],"") -> 3 | Q4: =IFERROR(tblRFM[[#This Row],[Satisfaction]],"") -> 3 | R4: =IFERROR(tblRFM[[#This Row],[RecommendationLikelihood]],"") -> 6 | S4: =COUNTIFS(tblTransactions[CustomerID],A4) -> 1 | T4: =IFERROR(INDEX(tblClean[DiscountSensitivity],MATCH(A4,tblClean[CustomerID],0)),"") -> Low | V4: Loyal | W4: =COUNTIFS(tblFinal[CustomerSegment],V4) -> 17 | X4: =IFERROR(SUMIFS(tblFinal[RFM_Monetary],tblFinal[CustomerSegment],V4),0) -> 1525892 | Y4: =IFERROR(X4/W4,0) -> 89758.353 | Z4: =IFERROR(AVERAGEIFS(tblFinal[RFM_Monetary],tblFinal[CustomerSegment],V4),0) -> 89758.353 | AA4: =COUNTIFS(tblFinal[CustomerSegment],V4,tblFinal[RFM_Monetary],">=50000") -> 17
A5: =tblRFM[[#This Row],[CustomerID]] -> C0003 | B5: =tblRFM[[#This Row],[Name]] -> Rohan Mehta | C5: =IFERROR(INDEX(tblClean[Gender],MATCH(A5,tblClean[CustomerID],0)),"") -> Male | D5: =tblRFM[[#This Row],[AgeGroup]] -> 25-39 | E5: =tblRFM[[#This Row],[City/Region]] -> Indore | F5: =tblRFM[[#This Row],[IncomeBracket]] -> Mid | G5: =tblRFM[[#This Row],[CustomerType]] -> Returning | H5: =tblRFM[[#This Row],[EngagementLevel]] -> Low | I5: =tblRFM[[#This Row],[CustomerSegment]] -> At Risk | J5: =tblRFM[[#This Row],[ProductPreference]] -> Grocery | K5: =IFERROR(INDEX(tblClean[PurchaseChannel],MATCH(A5,tblClean[CustomerID],0)),"") -> Online | L5: =tblRFM[[#This Row],[RFM_Recency]] -> 172 | M5: =tblRFM[[#This Row],[RFM_Frequency]] -> 2 | N5: =tblRFM[[#This Row],[RFM_Monetary]] -> 5380 | O5: =tblRFM[[#This Row],[RFM_Score]] -> 222 | P5: =IFERROR(tblRFM[[#This Row],[SatisfactionIndex]],"") -> 3.75 | Q5: =IFERROR(tblRFM[[#This Row],[Satisfaction]],"") -> 4 | R5: =IFERROR(tblRFM[[#This Row],[RecommendationLikelihood]],"") -> 7 | S5: =COUNTIFS(tblTransactions[CustomerID],A5) -> 2 | T5: =IFERROR(INDEX(tblClean[DiscountSensitivity],MATCH(A5,tblClean[CustomerID],0)),"") -> High | V5: High Value | W5: =COUNTIFS(tblFinal[CustomerSegment],V5) -> 74 | X5: =IFERROR(SUMIFS(tblFinal[RFM_Monetary],tblFinal[CustomerSegment],V5),0) -> 6607484 | Y5: =IFERROR(X5/W5,0) -> 89290.324 | Z5: =IFERROR(AVERAGEIFS(tblFinal[RFM_Monetary],tblFinal[CustomerSegment],V5),0) -> 89290.324 | AA5: =COUNTIFS(tblFinal[CustomerSegment],V5,tblFinal[RFM_Monetary],">=50000") -> 74
A6: =tblRFM[[#This Row],[CustomerID]] -> C0004 | B6: =tblRFM[[#This Row],[Name]] -> Nikhil Gupta | C6: =IFERROR(INDEX(tblClean[Gender],MATCH(A6,tblClean[CustomerID],0)),"") -> Male | D6: =tblRFM[[#This Row],[AgeGroup]] -> 40-54 | E6: =tblRFM[[#This Row],[City/Region]] -> Jaipur | F6: =tblRFM[[#This Row],[IncomeBracket]] -> Mid | G6: =tblRFM[[#This Row],[CustomerType]] -> New | H6: =tblRFM[[#This Row],[EngagementLevel]] -> Low | I6: =tblRFM[[#This Row],[CustomerSegment]] -> General | J6: =tblRFM[[#This Row],[ProductPreference]] -> Electronics | K6: =IFERROR(INDEX(tblClean[PurchaseChannel],MATCH(A6,tblClean[CustomerID],0)),"") -> Offline | L6: =tblRFM[[#This Row],[RFM_Recency]] -> 51 | M6: =tblRFM[[#This Row],[RFM_Frequency]] -> 1 | N6: =tblRFM[[#This Row],[RFM_Monetary]] -> 12070 | O6: =tblRFM[[#This Row],[RFM_Score]] -> 412 | P6: =IFERROR(tblRFM[[#This Row],[SatisfactionIndex]],"") -> 3 | Q6: =IFERROR(tblRFM[[#This Row],[Satisfaction]],"") -> 3 | R6: =IFERROR(tblRFM[[#This Row],[RecommendationLikelihood]],"") -> 6 | S6: =COUNTIFS(tblTransactions[CustomerID],A6) -> 1 | T6: =IFERROR(INDEX(tblClean[DiscountSensitivity],MATCH(A6,tblClean[CustomerID],0)),"") -> Low | V6: At Risk | W6: =COUNTIFS(tblFinal[CustomerSegment],V6) -> 38 | X6: =IFERROR(SUMIFS(tblFinal[RFM_Monetary],tblFinal[CustomerSegment],V6),0) -> 537567 | Y6: =IFERROR(X6/W6,0) -> 14146.5 | Z6: =IFERROR(AVERAGEIFS(tblFinal[RFM_Monetary],tblFinal[CustomerSegment],V6),0) -> 14146.5 | AA6: =COUNTIFS(tblFinal[CustomerSegment],V6,tblFinal[RFM_Monetary],">=50000") -> 0
A7: =tblRFM[[#This Row],[CustomerID]] -> C0005 | B7: =tblRFM[[#This Row],[Name]] -> Amit Verma | C7: =IFERROR(INDEX(tblClean[Gender],MATCH(A7,tblClean[CustomerID],0)),"") -> Male | D7: =tblRFM[[#This Row],[AgeGroup]] -> 40-54 | E7: =tblRFM[[#This Row],[City/Region]] -> Bhubaneswar | F7: =tblRFM[[#This Row],[IncomeBracket]] -> Mid | G7: =tblRFM[[#This Row],[CustomerType]] -> Returning | H7: =tblRFM[[#This Row],[EngagementLevel]] -> High | I7: =tblRFM[[#This Row],[CustomerSegment]] -> High Value | J7: =tblRFM[[#This Row],[ProductPreference]] -> Home Decor | K7: =IFERROR(INDEX(tblClean[PurchaseChannel],MATCH(A7,tblClean[CustomerID],0)),"") -> Offline | L7: =tblRFM[[#This Row],[RFM_Recency]] -> 112 | M7: =tblRFM[[#This Row],[RFM_Frequency]] -> 14 | N7: =tblRFM[[#This Row],[RFM_Monetary]] -> 66820 | O7: =tblRFM[[#This Row],[RFM_Score]] -> 255 | P7: =IFERROR(tblRFM[[#This Row],[SatisfactionIndex]],"") -> 3 | Q7: =IFERROR(tblRFM[[#This Row],[Satisfaction]],"") -> 4 | R7: =IFERROR(tblRFM[[#This Row],[RecommendationLikelihood]],"") -> 4 | S7: =COUNTIFS(tblTransactions[CustomerID],A7) -> 14 | T7: =IFERROR(INDEX(tblClean[DiscountSensitivity],MATCH(A7,tblClean[CustomerID],0)),"") -> Medium | V7: Bargain Seeker | W7: =COUNTIFS(tblFinal[CustomerSegment],V7) -> 8 | X7: =IFERROR(SUMIFS(tblFinal[RFM_Monetary],tblFinal[CustomerSegment],V7),0) -> 184330 | Y7: =IFERROR(X7/W7,0) -> 23041.25 | Z7: =IFERROR(AVERAGEIFS(tblFinal[RFM_Monetary],tblFinal[CustomerSegment],V7),0) -> 23041.25 | AA7: =COUNTIFS(tblFinal[CustomerSegment],V7,tblFinal[RFM_Monetary],">=50000") -> 0
A8: =tblRFM[[#This Row],[CustomerID]] -> C0006 | B8: =tblRFM[[#This Row],[Name]] -> Suresh Kumar | C8: =IFERROR(INDEX(tblClean[Gender],MATCH(A8,tblClean[CustomerID],0)),"") -> Male | D8: =tblRFM[[#This Row],[AgeGroup]] -> 40-54 | E8: =tblRFM[[#This Row],[City/Region]] -> Kolkata | F8: =tblRFM[[#This Row],[IncomeBracket]] -> High | G8: =tblRFM[[#This Row],[CustomerType]] -> Returning | H8: =tblRFM[[#This Row],[EngagementLevel]] -> Low | I8: =tblRFM[[#This Row],[CustomerSegment]] -> At Risk | J8: =tblRFM[[#This Row],[ProductPreference]] -> Grocery | K8: =IFERROR(INDEX(tblClean[PurchaseChannel],MATCH(A8,tblClean[CustomerID],0)),"") -> Online | L8: =tblRFM[[#This Row],[RFM_Recency]] -> 165 | M8: =tblRFM[[#This Row],[RFM_Frequency]] -> 1 | N8: =tblRFM[[#This Row],[RFM_Monetary]] -> 12330 | O8: =tblRFM[[#This Row],[RFM_Score]] -> 212 | P8: =IFERROR(tblRFM[[#This Row],[SatisfactionIndex]],"") -> 3.75 | Q8: =IFERROR(tblRFM[[#This Row],[Satisfaction]],"") -> 4 | R8: =IFERROR(tblRFM[[#This Row],[RecommendationLikelihood]],"") -> 7 | S8: =COUNTIFS(tblTransactions[CustomerID],A8) -> 1 | T8: =IFERROR(INDEX(tblClean[DiscountSensitivity],MATCH(A8,tblClean[CustomerID],0)),"") -> Low | V8: General | W8: =COUNTIFS(tblFinal[CustomerSegment],V8) -> 63 | X8: =IFERROR(SUMIFS(tblFinal[RFM_Monetary],tblFinal[CustomerSegment],V8),0) -> 1183500 | Y8: =IFERROR(X8/W8,0) -> 18785.714 | Z8: =IFERROR(AVERAGEIFS(tblFinal[RFM_Monetary],tblFinal[CustomerSegment],V8),0) -> 18785.714 | AA8: =COUNTIFS(tblFinal[CustomerSegment],V8,tblFinal[RFM_Monetary],">=50000") -> 0
A9: =tblRFM[[#This Row],[CustomerID]] -> C0007 | B9: =tblRFM[[#This Row],[Name]] -> Rajesh Patel | C9: =IFERROR(INDEX(tblClean[Gender],MATCH(A9,tblClean[CustomerID],0)),"") -> Male | D9: =tblRFM[[#This Row],[AgeGroup]] -> 25-39 | E9: =tblRFM[[#This Row],[City/Region]] -> Bangalore | F9: =tblRFM[[#This Row],[IncomeBracket]] -> High | G9: =tblRFM[[#This Row],[CustomerType]] -> Returning | H9: =tblRFM[[#This Row],[EngagementLevel]] -> High | I9: =tblRFM[[#This Row],[CustomerSegment]] -> High Value | J9: =tblRFM[[#This Row],[ProductPreference]] -> Clothing | K9: =IFERROR(INDEX(tblClean[PurchaseChannel],MATCH(A9,tblClean[CustomerID],0)),"") -> Online | L9: =tblRFM[[#This Row],[RFM_Recency]] -> 225 | M9: =tblRFM[[#This Row],[RFM_Frequency]] -> 14 | N9: =tblRFM[[#This Row],[RFM_Monetary]] -> 108600 | O9: =tblRFM[[#This Row],[RFM_Score]] -> 155 | P9: =IFERROR(tblRFM[[#This Row],[SatisfactionIndex]],"") -> 3 | Q9: =IFERROR(tblRFM[[#This Row],[Satisfaction]],"") -> 4 | R9: =IFERROR(tblRFM[[#This Row],[RecommendationLikelihood]],"") -> 4 | S9: =COUNTIFS(tblTransactions[CustomerID],A9) -> 14 | T9: =IFERROR(INDEX(tblClean[DiscountSensitivity],MATCH(A9,tblClean[CustomerID],0)),"") -> Low
A10: =tblRFM[[#This Row],[CustomerID]] -> C0008 | B10: =tblRFM[[#This Row],[Name]] -> Aditya Joshi | C10: =IFERROR(INDEX(tblClean[Gender],MATCH(A10,tblClean[CustomerID],0)),"") -> Male | D10: =tblRFM[[#This Row],[AgeGroup]] -> 40-54 | E10: =tblRFM[[#This Row],[City/Region]] -> Hyderabad | F10: =tblRFM[[#This Row],[IncomeBracket]] -> High | G10: =tblRFM[[#This Row],[CustomerType]] -> New | H10: =tblRFM[[#This Row],[EngagementLevel]] -> Medium | I10: =tblRFM[[#This Row],[CustomerSegment]] -> At Risk | J10: =tblRFM[[#This Row],[ProductPreference]] -> Grocery | K10: =IFERROR(INDEX(tblClean[PurchaseChannel],MATCH(A10,tblClean[CustomerID],0)),"") -> Offline | L10: =tblRFM[[#This Row],[RFM_Recency]] -> 93 | M10: =tblRFM[[#This Row],[RFM_Frequency]] -> 1 | N10: =tblRFM[[#This Row],[RFM_Monetary]] -> 570 | O10: =tblRFM[[#This Row],[RFM_Score]] -> 211 | P10: =IFERROR(tblRFM[[#This Row],[SatisfactionIndex]],"") -> 1.75 | Q10: =IFERROR(tblRFM[[#This Row],[Satisfaction]],"") -> 1 | R10: =IFERROR(tblRFM[[#This Row],[RecommendationLikelihood]],"") -> 5 | S10: =COUNTIFS(tblTransactions[CustomerID],A10) -> 1 | T10: =IFERROR(INDEX(tblClean[DiscountSensitivity],MATCH(A10,tblClean[CustomerID],0)),"") -> Low
A11: =tblRFM[[#This Row],[CustomerID]] -> C0009 | B11: =tblRFM[[#This Row],[Name]] -> Karan Kapoor | C11: =IFERROR(INDEX(tblClean[Gender],MATCH(A11,tblClean[CustomerID],0)),"") -> Male | D11: =tblRFM[[#This Row],[AgeGroup]] -> 40-54 | E11: =tblRFM[[#This Row],[City/Region]] -> Ahmedabad | F11: =tblRFM[[#This Row],[IncomeBracket]] -> High | G11: =tblRFM[[#This Row],[CustomerType]] -> New | H11: =tblRFM[[#This Row],[EngagementLevel]] -> High | I11: =tblRFM[[#This Row],[CustomerSegment]] -> At Risk | J11: =tblRFM[[#This Row],[ProductPreference]] -> Grocery | K11: =IFERROR(INDEX(tblClean[PurchaseChannel],MATCH(A11,tblClean[CustomerID],0)),"") -> Online | L11: =tblRFM[[#This Row],[RFM_Recency]] -> 92 | M11: =tblRFM[[#This Row],[RFM_Frequency]] -> 1 | N11: =tblRFM[[#This Row],[RFM_Monetary]] -> 6730 | O11: =tblRFM[[#This Row],[RFM_Score]] -> 212 | P11: =IFERROR(tblRFM[[#This Row],[SatisfactionIndex]],"") -> 4.25 | Q11: =IFERROR(tblRFM[[#This Row],[Satisfaction]],"") -> 4 | R11: =IFERROR(tblRFM[[#This Row],[RecommendationLikelihood]],"") -> 9 | S11: =COUNTIFS(tblTransactions[CustomerID],A11) -> 1 | T11: =IFERROR(INDEX(tblClean[DiscountSensitivity],MATCH(A11,tblClean[CustomerID],0)),"") -> Low
A12: =tblRFM[[#This Row],[CustomerID]] -> C0010 | B12: =tblRFM[[#This Row],[Name]] -> Deepak Nair | C12: =IFERROR(INDEX(tblClean[Gender],MATCH(A12,tblClean[CustomerID],0)),"") -> Male | D12: =tblRFM[[#This Row],[AgeGroup]] -> <25 | E12: =tblRFM[[#This Row],[City/Region]] -> Jaipur | F12: =tblRFM[[#This Row],[IncomeBracket]] -> Mid | G12: =tblRFM[[#This Row],[CustomerType]] -> Returning | H12: =tblRFM[[#This Row],[EngagementLevel]] -> High | I12: =tblRFM[[#This Row],[CustomerSegment]] -> High Value | J12: =tblRFM[[#This Row],[ProductPreference]] -> Sports | K12: =IFERROR(INDEX(tblClean[PurchaseChannel],MATCH(A12,tblClean[CustomerID],0)),"") -> Online | L12: =tblRFM[[#This Row],[RFM_Recency]] -> 40 | M12: =tblRFM[[#This Row],[RFM_Frequency]] -> 14 | N12: =tblRFM[[#This Row],[RFM_Monetary]] -> 51230 | O12: =tblRFM[[#This Row],[RFM_Score]] -> 455 | P12: =IFERROR(tblRFM[[#This Row],[SatisfactionIndex]],"") -> 3 | Q12: =IFERROR(tblRFM[[#This Row],[Satisfaction]],"") -> 3 | R12: =IFERROR(tblRFM[[#This Row],[RecommendationLikelihood]],"") -> 6 | S12: =COUNTIFS(tblTransactions[CustomerID],A12) -> 14 | T12: =IFERROR(INDEX(tblClean[DiscountSensitivity],MATCH(A12,tblClean[CustomerID],0)),"") -> Medium
A13: =tblRFM[[#This Row],[CustomerID]] -> C0011 | B13: =tblRFM[[#This Row],[Name]] -> Manish Tiwari | C13: =IFERROR(INDEX(tblClean[Gender],MATCH(A13,tblClean[CustomerID],0)),"") -> Male | D13: =tblRFM[[#This Row],[AgeGroup]] -> 55+ | E13: =tblRFM[[#This Row],[City/Region]] -> Bhopal | F13: =tblRFM[[#This Row],[IncomeBracket]] -> Mid | G13: =tblRFM[[#This Row],[CustomerType]] -> New | H13: =tblRFM[[#This Row],[EngagementLevel]] -> Medium | I13: =tblRFM[[#This Row],[CustomerSegment]] -> General | J13: =tblRFM[[#This Row],[ProductPreference]] -> Beauty | K13: =IFERROR(INDEX(tblClean[PurchaseChannel],MATCH(A13,tblClean[CustomerID],0)),"") -> Online | L13: =tblRFM[[#This Row],[RFM_Recency]] -> 66 | M13: =tblRFM[[#This Row],[RFM_Frequency]] -> 1 | N13: =tblRFM[[#This Row],[RFM_Monetary]] -> 3660 | O13: =tblRFM[[#This Row],[RFM_Score]] -> 311 | P13: =IFERROR(tblRFM[[#This Row],[SatisfactionIndex]],"") -> 4 | Q13: =IFERROR(tblRFM[[#This Row],[Satisfaction]],"") -> 4 | R13: =IFERROR(tblRFM[[#This Row],[RecommendationLikelihood]],"") -> 8 | S13: =COUNTIFS(tblTransactions[CustomerID],A13) -> 1 | T13: =IFERROR(INDEX(tblClean[DiscountSensitivity],MATCH(A13,tblClean[CustomerID],0)),"") -> Medium
A14: =tblRFM[[#This Row],[CustomerID]] -> C0012 | B14: =tblRFM[[#This Row],[Name]] -> Gaurav Saxena | C14: =IFERROR(INDEX(tblClean[Gender],MATCH(A14,tblClean[CustomerID],0)),"") -> Male | D14: =tblRFM[[#This Row],[AgeGroup]] -> 55+ | E14: =tblRFM[[#This Row],[City/Region]] -> Lucknow | F14: =tblRFM[[#This Row],[IncomeBracket]] -> High | G14: =tblRFM[[#This Row],[CustomerType]] -> Returning | H14: =tblRFM[[#This Row],[EngagementLevel]] -> Low | I14: =tblRFM[[#This Row],[CustomerSegment]] -> At Risk | J14: =tblRFM[[#This Row],[ProductPreference]] -> Grocery | K14: =IFERROR(INDEX(tblClean[PurchaseChannel],MATCH(A14,tblClean[CustomerID],0)),"") -> Online | L14: =tblRFM[[#This Row],[RFM_Recency]] -> 160 | M14: =tblRFM[[#This Row],[RFM_Frequency]] -> 2 | N14: =tblRFM[[#This Row],[RFM_Monetary]] -> 5290 | O14: =tblRFM[[#This Row],[RFM_Score]] -> 222 | P14: =IFERROR(tblRFM[[#This Row],[SatisfactionIndex]],"") -> 4 | Q14: =IFERROR(tblRFM[[#This Row],[Satisfaction]],"") -> 4 | R14: =IFERROR(tblRFM[[#This Row],[RecommendationLikelihood]],"") -> 8 | S14: =COUNTIFS(tblTransactions[CustomerID],A14) -> 2 | T14: =IFERROR(INDEX(tblClean[DiscountSensitivity],MATCH(A14,tblClean[CustomerID],0)),"") -> Medium
A15: =tblRFM[[#This Row],[CustomerID]] -> C0013 | B15: =tblRFM[[#This Row],[Name]] -> Sanjay Yadav | C15: =IFERROR(INDEX(tblClean[Gender],MATCH(A15,tblClean[CustomerID],0)),"") -> Male | D15: =tblRFM[[#This Row],[AgeGroup]] -> <25 | E15: =tblRFM[[#This Row],[City/Region]] -> Noida | F15: =tblRFM[[#This Row],[IncomeBracket]] -> Mid | G15: =tblRFM[[#This Row],[CustomerType]] -> Returning | H15: =tblRFM[[#This Row],[EngagementLevel]] -> Low | I15: =tblRFM[[#This Row],[CustomerSegment]] -> Loyal | J15: =tblRFM[[#This Row],[ProductPreference]] -> Sports | K15: =IFERROR(INDEX(tblClean[PurchaseChannel],MATCH(A15,tblClean[CustomerID],0)),"") -> Offline | L15: =tblRFM[[#This Row],[RFM_Recency]] -> 29 | M15: =tblRFM[[#This Row],[RFM_Frequency]] -> 14 | N15: =tblRFM[[#This Row],[RFM_Monetary]] -> 93470 | O15: =tblRFM[[#This Row],[RFM_Score]] -> 555 | P15: =IFERROR(tblRFM[[#This Row],[SatisfactionIndex]],"") -> 3.5 | Q15: =IFERROR(tblRFM[[#This Row],[Satisfaction]],"") -> 3 | R15: =IFERROR(tblRFM[[#This Row],[RecommendationLikelihood]],"") -> 8 | S15: =COUNTIFS(tblTransactions[CustomerID],A15) -> 14 | T15: =IFERROR(INDEX(tblClean[DiscountSensitivity],MATCH(A15,tblClean[CustomerID],0)),"") -> Medium
A16: =tblRFM[[#This Row],[CustomerID]] -> C0014 | B16: =tblRFM[[#This Row],[Name]] -> Rahul Mishra | C16: =IFERROR(INDEX(tblClean[Gender],MATCH(A16,tblClean[CustomerID],0)),"") -> Male | D16: =tblRFM[[#This Row],[AgeGroup]] -> 40-54 | E16: =tblRFM[[#This Row],[City/Region]] -> Surat | F16: =tblRFM[[#This Row],[IncomeBracket]] -> Mid | G16: =tblRFM[[#This Row],[CustomerType]] -> New | H16: =tblRFM[[#This Row],[EngagementLevel]] -> High | I16: =tblRFM[[#This Row],[CustomerSegment]] -> General | J16: =tblRFM[[#This Row],[ProductPreference]] -> Grocery | K16: =IFERROR(INDEX(tblClean[PurchaseChannel],MATCH(A16,tblClean[CustomerID],0)),"") -> Offline | L16: =tblRFM[[#This Row],[RFM_Recency]] -> 81 | M16: =tblRFM[[#This Row],[RFM_Frequency]] -> 1 | N16: =tblRFM[[#This Row],[RFM_Monetary]] -> 17170 | O16: =tblRFM[[#This Row],[RFM_Score]] -> 313 | P16: =IFERROR(tblRFM[[#This Row],[SatisfactionIndex]],"") -> 3.25 | Q16: =IFERROR(tblRFM[[#This Row],[Satisfaction]],"") -> 4 | R16: =IFERROR(tblRFM[[#This Row],[RecommendationLikelihood]],"") -> 5 | S16: =COUNTIFS(tblTransactions[CustomerID],A16) -> 1 | T16: =IFERROR(INDEX(tblClean[DiscountSensitivity],MATCH(A16,tblClean[CustomerID],0)),"") -> High
A17: =tblRFM[[#This Row],[CustomerID]] -> C0015 | B17: =tblRFM[[#This Row],[Name]] -> Varun Chopra | C17: =IFERROR(INDEX(tblClean[Gender],MATCH(A17,tblClean[CustomerID],0)),"") -> Male | D17: =tblRFM[[#This Row],[AgeGroup]] -> 55+ | E17: =tblRFM[[#This Row],[City/Region]] -> Jaipur | F17: =tblRFM[[#This Row],[IncomeBracket]] -> Mid | G17: =tblRFM[[#This Row],[CustomerType]] -> New | H17: =tblRFM[[#This Row],[EngagementLevel]] -> Medium | I17: =tblRFM[[#This Row],[CustomerSegment]] -> General | J17: =tblRFM[[#This Row],[ProductPreference]] -> Electronics | K17: =IFERROR(INDEX(tblClean[PurchaseChannel],MATCH(A17,tblClean[CustomerID],0)),"") -> Online | L17: =tblRFM[[#This Row],[RFM_Recency]] -> 65 | M17: =tblRFM[[#This Row],[RFM_Frequency]] -> 1 | N17: =tblRFM[[#This Row],[RFM_Monetary]] -> 4430 | O17: =tblRFM[[#This Row],[RFM_Score]] -> 311 | P17: =IFERROR(tblRFM[[#This Row],[SatisfactionIndex]],"") -> 4 | Q17: =IFERROR(tblRFM[[#This Row],[Satisfaction]],"") -> 5 | R17: =IFERROR(tblRFM[[#This Row],[RecommendationLikelihood]],"") -> 6 | S17: =COUNTIFS(tblTransactions[CustomerID],A17) -> 1 | T17: =IFERROR(INDEX(tblClean[DiscountSensitivity],MATCH(A17,tblClean[CustomerID],0)),"") -> High
A18: =tblRFM[[#This Row],[CustomerID]] -> C0016 | B18: =tblRFM[[#This Row],[Name]] -> Harish Reddy | C18: =IFERROR(INDEX(tblClean[Gender],MATCH(A18,tblClean[CustomerID],0)),"") -> Male | D18: =tblRFM[[#This Row],[AgeGroup]] -> 40-54 | E18: =tblRFM[[#This Row],[City/Region]] -> Chennai | F18: =tblRFM[[#This Row],[IncomeBracket]] -> High | G18: =tblRFM[[#This Row],[CustomerType]] -> New | H18: =tblRFM[[#This Row],[EngagementLevel]] -> Medium | I18: =tblRFM[[#This Row],[CustomerSegment]] -> At Risk | J18: =tblRFM[[#This Row],[ProductPreference]] -> Sports | K18: =IFERROR(INDEX(tblClean[PurchaseChannel],MATCH(A18,tblClean[CustomerID],0)),"") -> Offline | L18: =tblRFM[[#This Row],[RFM_Recency]] -> 262 | M18: =tblRFM[[#This Row],[RFM_Frequency]] -> 1 | N18: =tblRFM[[#This Row],[RFM_Monetary]] -> 2170 | O18: =tblRFM[[#This Row],[RFM_Score]] -> 111 | P18: =IFERROR(tblRFM[[#This Row],[SatisfactionIndex]],"") -> 2.75 | Q18: =IFERROR(tblRFM[[#This Row],[Satisfaction]],"") -> 2 | R18: =IFERROR(tblRFM[[#This Row],[RecommendationLikelihood]],"") -> 7 | S18: =COUNTIFS(tblTransactions[CustomerID],A18) -> 1 | T18: =IFERROR(INDEX(tblClean[DiscountSensitivity],MATCH(A18,tblClean[CustomerID],0)),"") -> Medium
A19: =tblRFM[[#This Row],[CustomerID]] -> C0017 | B19: =tblRFM[[#This Row],[Name]] -> Pradeep Iyer | C19: =IFERROR(INDEX(tblClean[Gender],MATCH(A19,tblClean[CustomerID],0)),"") -> Male | D19: =tblRFM[[#This Row],[AgeGroup]] -> 25-39 | E19: =tblRFM[[#This Row],[City/Region]] -> Chandigarh | F19: =tblRFM[[#This Row],[IncomeBracket]] -> High | G19: =tblRFM[[#This Row],[CustomerType]] -> Returning | H19: =tblRFM[[#This Row],[EngagementLevel]] -> High | I19: =tblRFM[[#This Row],[CustomerSegment]] -> High Value | J19: =tblRFM[[#This Row],[ProductPreference]] -> Home Decor | K19: =IFERROR(INDEX(tblClean[PurchaseChannel],MATCH(A19,tblClean[CustomerID],0)),"") -> Offline | L19: =tblRFM[[#This Row],[RFM_Recency]] -> 56 | M19: =tblRFM[[#This Row],[RFM_Frequency]] -> 12 | N19: =tblRFM[[#This Row],[RFM_Monetary]] -> 57460 | O19: =tblRFM[[#This Row],[RFM_Score]] -> 455 | P19: =IFERROR(tblRFM[[#This Row],[SatisfactionIndex]],"") -> 3.25 | Q19: =IFERROR(tblRFM[[#This Row],[Satisfaction]],"") -> 3 | R19: =IFERROR(tblRFM[[#This Row],[RecommendationLikelihood]],"") -> 7 | S19: =COUNTIFS(tblTransactions[CustomerID],A19) -> 12 | T19: =IFERROR(INDEX(tblClean[DiscountSensitivity],MATCH(A19,tblClean[CustomerID],0)),"") -> Medium
A20: =tblRFM[[#This Row],[CustomerID]] -> C0018 | B20: =tblRFM[[#This Row],[Name]] -> Ankit Dubey | C20: =IFERROR(INDEX(tblClean[Gender],MATCH(A20,tblClean[CustomerID],0)),"") -> Male | D20: =tblRFM[[#This Row],[AgeGroup]] -> 40-54 | E20: =tblRFM[[#This Row],[City/Region]] -> Delhi | F20: =tblRFM[[#This Row],[IncomeBracket]] -> Mid | G20: =tblRFM[[#This Row],[CustomerType]] -> Returning | H20: =tblRFM[[#This Row],[EngagementLevel]] -> Medium | I20: =tblRFM[[#This Row],[CustomerSegment]] -> Bargain Seeker | J20: =tblRFM[[#This Row],[ProductPreference]] -> Clothing | K20: =IFERROR(INDEX(tblClean[PurchaseChannel],MATCH(A20,tblClean[CustomerID],0)),"") -> Offline | L20: =tblRFM[[#This Row],[RFM_Recency]] -> 13 | M20: =tblRFM[[#This Row],[RFM_Frequency]] -> 5 | N20: =tblRFM[[#This Row],[RFM_Monetary]] -> 22010 | O20: =tblRFM[[#This Row],[RFM_Score]] -> 533 | P20: =IFERROR(tblRFM[[#This Row],[SatisfactionIndex]],"") -> 3.75 | Q20: =IFERROR(tblRFM[[#This Row],[Satisfaction]],"") -> 4 | R20: =IFERROR(tblRFM[[#This Row],[RecommendationLikelihood]],"") -> 7 | S20: =COUNTIFS(tblTransactions[CustomerID],A20) -> 5 | T20: =IFERROR(INDEX(tblClean[DiscountSensitivity],MATCH(A20,tblClean[CustomerID],0)),"") -> Low
... A202: =tblRFM[[#This Row],[CustomerID]] -> C0200 | B202: =tblRFM[[#This Row],[Name]] -> Manoj Pillai | C202: =IFERROR(INDEX(tblClean[Gender],MATCH(A202,tblClean[CustomerID],0)),"") -> Male | D202: =tblRFM[[#This Row],[AgeGroup]] -> 25-39 | E202: =tblRFM[[#This Row],[City/Region]] -> Lucknow | F202: =tblRFM[[#This Row],[IncomeBracket]] -> Mid | G202: =tblRFM[[#This Row],[CustomerType]] -> Returning | H202: =tblRFM[[#This Row],[EngagementLevel]] -> Medium | I202: =tblRFM[[#This Row],[CustomerSegment]] -> High Value | J202: =tblRFM[[#This Row],[ProductPreference]] -> Grocery | K202: =IFERROR(INDEX(tblClean[PurchaseChannel],MATCH(A202,tblClean[CustomerID],0)),"") -> Offline | L202: =tblRFM[[#This Row],[RFM_Recency]] -> 374 | M202: =tblRFM[[#This Row],[RFM_Frequency]] -> 4 | N202: =tblRFM[[#This Row],[RFM_Monetary]] -> 52070 | O202: =tblRFM[[#This Row],[RFM_Score]] -> 135 | P202: =IFERROR(tblRFM[[#This Row],[SatisfactionIndex]],"") -> 3 | Q202: =IFERROR(tblRFM[[#This Row],[Satisfaction]],"") -> 1 | R202: =IFERROR(tblRFM[[#This Row],[RecommendationLikelihood]],"") -> 10 | S202: =COUNTIFS(tblTransactions[CustomerID],A202) -> 4 | T202: =IFERROR(INDEX(tblClean[DiscountSensitivity],MATCH(A202,tblClean[CustomerID],0)),"") -> Low
A204: 📊 Pivot 1 — Customers by Segment | Source: tblFinal | Rows: CustomerSegment | Values: Count of CustomerID
A205: Row Labels | B205: Count of CustomerID
A206: At Risk | B206: 38
A207: Bargain Seeker | B207: 8
A208: General | B208: 63
A209: High Value | B209: 74
A210: Loyal | B210: 17
A211: Grand Total | B211: 200
A214: 💰 Pivot 2 — Revenue by Segment | Source: tblFinal | Rows: CustomerSegment | Values: Sum of RFM_Monetary (INR)
A215: Row Labels | B215: Sum of RFM_Monetary
A216: At Risk | B216: 537567
A217: Bargain Seeker | B217: 184330
A218: General | B218: 1183500
A219: High Value | B219: 6607484
A220: Loyal | B220: 1525892
A221: Grand Total | B221: 10038773
A224: 🍩 Pivot 3 — Customer Distribution by Age Group | Source: tblFinal | Rows: AgeGroup | Values: Count of CustomerID
A225: Row Labels | B225: Count of CustomerID
A226: <25 | B226: 16
A227: 25-39 | B227: 67
A228: 40-54 | B228: 68
A229: 55+ | B229: 49
A230: Grand Total | B230: 200
A235: 📈 Pivot 4 — Monthly Revenue Trend | Source: tblTransactions | Rows: TxnMonth | Values: Sum of Amount (INR)
A236: Monthly Revenue Trend
A238: Row Labels | B238: Sum of Amount (INR)
A239: 2025-04 | B239: 789074
A240: 2025-05 | B240: 712840
A241: 2025-06 | B241: 860066
A242: 2025-07 | B242: 691483
A243: 2025-08 | B243: 888188
A244: 2025-09 | B244: 950923
A245: 2025-10 | B245: 928409
A246: 2025-11 | B246: 786785
A247: 2025-12 | B247: 711043
A248: 2026-01 | B248: 1061743
A249: 2026-02 | B249: 866572
A250: 2026-03 | B250: 791647
A251: Grand Total | B251: 10038773
A253: 📈 Pivot 5 — Analysis by Region | Source: tblTransactions
A254: Row Labels | B254: Count of CustomerID | C254: Sum of RFM_Monetary
A255: Ahmedabad | B255: 19 | C255: 666456
A256: Bangalore | B256: 14 | C256: 792765
A257: Bhopal | B257: 9 | C257: 479969
A258: Bhubaneswar | B258: 11 | C258: 663318
A259: Chandigarh | B259: 8 | C259: 445218
A260: Chennai | B260: 11 | C260: 751340
A261: Coimbatore | B261: 4 | C261: 207197
A262: Delhi | B262: 8 | C262: 275789
A263: Faridabad | B263: 2 | C263: 18490
A264: Gurgaon | B264: 2 | C264: 111010
A265: Hyderabad | B265: 8 | C265: 396008
A266: Indore | B266: 9 | C266: 405192
... A278: Grand Total | B278: 200 | C278: 10038773

Sheet Lookup Tables
A1: 📌 tblSegments — Segment Criteria & Definitions | E1: 📅 tblCalendar — FY 2025-26 Date Reference | M1: 📅 Report As-Of Date
A2: SegmentName | B2: CriteriaDescription | C2: Color Code | E2: Date | F2: Year | G2: Month | H2: MonthName | I2: Weekday | J2: IsWeekend | K2: FY_Quarter | M2: Report Date: | N2: =TODAY() -> 46125
A3: Loyal | B3: RFM_Score = '555' OR SatisfactionIndex ≥ 4.5 | C3: #4472C4 | E3: 45748 | F3: 2025 | G3: 4 | H3: April | I3: Tuesday | J3: =FALSE() -> FALSE | K3: Q1
A4: High Value | B4: RFM_Monetary ≥ ₹50,000 AND not already Loyal | C4: #70AD47 | E4: 45749 | F4: 2025 | G4: 4 | H4: April | I4: Wednesday | J4: =FALSE() -> FALSE | K4: Q1
A5: At Risk | B5: RFM_Recency > 90 days AND RFM_Frequency < 3 | C5: #FF6B6B | E5: 45750 | F5: 2025 | G5: 4 | H5: April | I5: Thursday | J5: =FALSE() -> FALSE | K5: Q1
A6: Bargain Seeker | B6: Monetary < ₹5,000 AND Frequency ≥ 5 | C6: #FFC000 | E6: 45751 | F6: 2025 | G6: 4 | H6: April | I6: Friday | J6: =FALSE() -> FALSE | K6: Q1
A7: General | B7: All other customers not in above segments | C7: #A9A9A9 | E7: 45752 | F7: 2025 | G7: 4 | H7: April | I7: Saturday | J7: =TRUE() -> TRUE | K7: Q1
E8: 45753 | F8: 2025 | G8: 4 | H8: April | I8: Sunday | J8: =TRUE() -> TRUE | K8: Q1
E9: 45754 | F9: 2025 | G9: 4 | H9: April | I9: Monday | J9: =FALSE() -> FALSE | K9: Q1
E10: 45755 | F10: 2025 | G10: 4 | H10: April | I10: Tuesday | J10: =FALSE() -> FALSE | K10: Q1
E11: 45756 | F11: 2025 | G11: 4 | H11: April | I11: Wednesday | J11: =FALSE() -> FALSE | K11: Q1
E12: 45757 | F12: 2025 | G12: 4 | H12: April | I12: Thursday | J12: =FALSE() -> FALSE | K12: Q1
E13: 45758 | F13: 2025 | G13: 4 | H13: April | I13: Friday | J13: =FALSE() -> FALSE | K13: Q1
E14: 45759 | F14: 2025 | G14: 4 | H14: April | I14: Saturday | J14: =TRUE() -> TRUE | K14: Q1
E15: 45760 | F15: 2025 | G15: 4 | H15: April | I15: Sunday | J15: =TRUE() -> TRUE | K15: Q1
E16: 45761 | F16: 2025 | G16: 4 | H16: April | I16: Monday | J16: =FALSE() -> FALSE | K16: Q1
E17: 45762 | F17: 2025 | G17: 4 | H17: April | I17: Tuesday | J17: =FALSE() -> FALSE | K17: Q1
E18: 45763 | F18: 2025 | G18: 4 | H18: April | I18: Wednesday | J18: =FALSE() -> FALSE | K18: Q1
E19: 45764 | F19: 2025 | G19: 4 | H19: April | I19: Thursday | J19: =FALSE() -> FALSE | K19: Q1
E20: 45765 | F20: 2025 | G20: 4 | H20: April | I20: Friday | J20: =FALSE() -> FALSE | K20: Q1
E21: 45766 | F21: 2025 | G21: 4 | H21: April | I21: Saturday | J21: =TRUE() -> TRUE | K21: Q1
E22: 45767 | F22: 2025 | G22: 4 | H22: April | I22: Sunday | J22: =TRUE() -> TRUE | K22: Q1
E23: 45768 | F23: 2025 | G23: 4 | H23: April | I23: Monday | J23: =FALSE() -> FALSE | K23: Q1
E24: 45769 | F24: 2025 | G24: 4 | H24: April | I24: Tuesday | J24: =FALSE() -> FALSE | K24: Q1
E25: 45770 | F25: 2025 | G25: 4 | H25: April | I25: Wednesday | J25: =FALSE() -> FALSE | K25: Q1
E26: 45771 | F26: 2025 | G26: 4 | H26: April | I26: Thursday | J26: =FALSE() -> FALSE | K26: Q1
E27: 45772 | F27: 2025 | G27: 4 | H27: April | I27: Friday | J27: =FALSE() -> FALSE | K27: Q1
E28: 45773 | F28: 2025 | G28: 4 | H28: April | I28: Saturday | J28: =TRUE() -> TRUE | K28: Q1
E29: 45774 | F29: 2025 | G29: 4 | H29: April | I29: Sunday | J29: =TRUE() -> TRUE | K29: Q1
E30: 45775 | F30: 2025 | G30: 4 | H30: April | I30: Monday | J30: =FALSE() -> FALSE | K30: Q1
E31: 45776 | F31: 2025 | G31: 4 | H31: April | I31: Tuesday | J31: =FALSE() -> FALSE | K31: Q1
E32: 45777 | F32: 2025 | G32: 4 | H32: April | I32: Wednesday | J32: =FALSE() -> FALSE | K32: Q1
E33: 45778 | F33: 2025 | G33: 5 | H33: May | I33: Thursday | J33: =FALSE() -> FALSE | K33: Q1
E34: 45779 | F34: 2025 | G34: 5 | H34: May | I34: Friday | J34: =FALSE() -> FALSE | K34: Q1
E35: 45780 | F35: 2025 | G35: 5 | H35: May | I35: Saturday | J35: =TRUE() -> TRUE | K35: Q1
E36: 45781 | F36: 2025 | G36: 5 | H36: May | I36: Sunday | J36: =TRUE() -> TRUE | K36: Q1
E37: 45782 | F37: 2025 | G37: 5 | H37: May | I37: Monday | J37: =FALSE() -> FALSE | K37: Q1
E38: 45783 | F38: 2025 | G38: 5 | H38: May | I38: Tuesday | J38: =FALSE() -> FALSE | K38: Q1
E39: 45784 | F39: 2025 | G39: 5 | H39: May | I39: Wednesday | J39: =FALSE() -> FALSE | K39: Q1
E40: 45785 | F40: 2025 | G40: 5 | H40: May | I40: Thursday | J40: =FALSE() -> FALSE | K40: Q1
E41: 45786 | F41: 2025 | G41: 5 | H41: May | I41: Friday | J41: =FALSE() -> FALSE | K41: Q1
E42: 45787 | F42: 2025 | G42: 5 | H42: May | I42: Saturday | J42: =TRUE() -> TRUE | K42: Q1
E43: 45788 | F43: 2025 | G43: 5 | H43: May | I43: Sunday | J43: =TRUE() -> TRUE | K43: Q1
E44: 45789 | F44: 2025 | G44: 5 | H44: May | I44: Monday | J44: =FALSE() -> FALSE | K44: Q1
E45: 45790 | F45: 2025 | G45: 5 | H45: May | I45: Tuesday | J45: =FALSE() -> FALSE | K45: Q1
E46: 45791 | F46: 2025 | G46: 5 | H46: May | I46: Wednesday | J46: =FALSE() -> FALSE | K46: Q1
E47: 45792 | F47: 2025 | G47: 5 | H47: May | I47: Thursday | J47: =FALSE() -> FALSE | K47: Q1
E48: 45793 | F48: 2025 | G48: 5 | H48: May | I48: Friday | J48: =FALSE() -> FALSE | K48: Q1
E49: 45794 | F49: 2025 | G49: 5 | H49: May | I49: Saturday | J49: =TRUE() -> TRUE | K49: Q1
E50: 45795 | F50: 2025 | G50: 5 | H50: May | I50: Sunday | J50: =TRUE() -> TRUE | K50: Q1
E51: 45796 | F51: 2025 | G51: 5 | H51: May | I51: Monday | J51: =FALSE() -> FALSE | K51: Q1
E52: 45797 | F52: 2025 | G52: 5 | H52: May | I52: Tuesday | J52: =FALSE() -> FALSE | K52: Q1
E53: 45798 | F53: 2025 | G53: 5 | H53: May | I53: Wednesday | J53: =FALSE() -> FALSE | K53: Q1
E54: 45799 | F54: 2025 | G54: 5 | H54: May | I54: Thursday | J54: =FALSE() -> FALSE | K54: Q1
E55: 45800 | F55: 2025 | G55: 5 | H55: May | I55: Friday | J55: =FALSE() -> FALSE | K55: Q1
E56: 45801 | F56: 2025 | G56: 5 | H56: May | I56: Saturday | J56: =TRUE() -> TRUE | K56: Q1
E57: 45802 | F57: 2025 | G57: 5 | H57: May | I57: Sunday | J57: =TRUE() -> TRUE | K57: Q1
E58: 45803 | F58: 2025 | G58: 5 | H58: May | I58: Monday | J58: =FALSE() -> FALSE | K58: Q1
E59: 45804 | F59: 2025 | G59: 5 | H59: May | I59: Tuesday | J59: =FALSE() -> FALSE | K59: Q1
E60: 45805 | F60: 2025 | G60: 5 | H60: May | I60: Wednesday | J60: =FALSE() -> FALSE | K60: Q1
E61: 45806 | F61: 2025 | G61: 5 | H61: May | I61: Thursday | J61: =FALSE() -> FALSE | K61: Q1
E62: 45807 | F62: 2025 | G62: 5 | H62: May | I62: Friday | J62: =FALSE() -> FALSE | K62: Q1
E63: 45808 | F63: 2025 | G63: 5 | H63: May | I63: Saturday | J63: =TRUE() -> TRUE | K63: Q1
E64: 45809 | F64: 2025 | G64: 6 | H64: June | I64: Sunday | J64: =TRUE() -> TRUE | K64: Q1
E65: 45810 | F65: 2025 | G65: 6 | H65: June | I65: Monday | J65: =FALSE() -> FALSE | K65: Q1
E66: 45811 | F66: 2025 | G66: 6 | H66: June | I66: Tuesday | J66: =FALSE() -> FALSE | K66: Q1
E67: 45812 | F67: 2025 | G67: 6 | H67: June | I67: Wednesday | J67: =FALSE() -> FALSE | K67: Q1
E68: 45813 | F68: 2025 | G68: 6 | H68: June | I68: Thursday | J68: =FALSE() -> FALSE | K68: Q1
E69: 45814 | F69: 2025 | G69: 6 | H69: June | I69: Friday | J69: =FALSE() -> FALSE | K69: Q1
E70: 45815 | F70: 2025 | G70: 6 | H70: June | I70: Saturday | J70: =TRUE() -> TRUE | K70: Q1
E71: 45816 | F71: 2025 | G71: 6 | H71: June | I71: Sunday | J71: =TRUE() -> TRUE | K71: Q1
E72: 45817 | F72: 2025 | G72: 6 | H72: June | I72: Monday | J72: =FALSE() -> FALSE | K72: Q1
E73: 45818 | F73: 2025 | G73: 6 | H73: June | I73: Tuesday | J73: =FALSE() -> FALSE | K73: Q1
E74: 45819 | F74: 2025 | G74: 6 | H74: June | I74: Wednesday | J74: =FALSE() -> FALSE | K74: Q1
E75: 45820 | F75: 2025 | G75: 6 | H75: June | I75: Thursday | J75: =FALSE() -> FALSE | K75: Q1
E76: 45821 | F76: 2025 | G76: 6 | H76: June | I76: Friday | J76: =FALSE() -> FALSE | K76: Q1
E77: 45822 | F77: 2025 | G77: 6 | H77: June | I77: Saturday | J77: =TRUE() -> TRUE | K77: Q1
E78: 45823 | F78: 2025 | G78: 6 | H78: June | I78: Sunday | J78: =TRUE() -> TRUE | K78: Q1
E79: 45824 | F79: 2025 | G79: 6 | H79: June | I79: Monday | J79: =FALSE() -> FALSE | K79: Q1
E80: 45825 | F80: 2025 | G80: 6 | H80: June | I80: Tuesday | J80: =FALSE() -> FALSE | K80: Q1
E81: 45826 | F81: 2025 | G81: 6 | H81: June | I81: Wednesday | J81: =FALSE() -> FALSE | K81: Q1
E82: 45827 | F82: 2025 | G82: 6 | H82: June | I82: Thursday | J82: =FALSE() -> FALSE | K82: Q1
E83: 45828 | F83: 2025 | G83: 6 | H83: June | I83: Friday | J83: =FALSE() -> FALSE | K83: Q1
E84: 45829 | F84: 2025 | G84: 6 | H84: June | I84: Saturday | J84: =TRUE() -> TRUE | K84: Q1
E85: 45830 | F85: 2025 | G85: 6 | H85: June | I85: Sunday | J85: =TRUE() -> TRUE | K85: Q1
E86: 45831 | F86: 2025 | G86: 6 | H86: June | I86: Monday | J86: =FALSE() -> FALSE | K86: Q1
E87: 45832 | F87: 2025 | G87: 6 | H87: June | I87: Tuesday | J87: =FALSE() -> FALSE | K87: Q1
E88: 45833 | F88: 2025 | G88: 6 | H88: June | I88: Wednesday | J88: =FALSE() -> FALSE | K88: Q1
E89: 45834 | F89: 2025 | G89: 6 | H89: June | I89: Thursday | J89: =FALSE() -> FALSE | K89: Q1
E90: 45835 | F90: 2025 | G90: 6 | H90: June | I90: Friday | J90: =FALSE() -> FALSE | K90: Q1
E91: 45836 | F91: 2025 | G91: 6 | H91: June | I91: Saturday | J91: =TRUE() -> TRUE | K91: Q1
E92: 45837 | F92: 2025 | G92: 6 | H92: June | I92: Sunday | J92: =TRUE() -> TRUE | K92: Q1
E93: 45838 | F93: 2025 | G93: 6 | H93: June | I93: Monday | J93: =FALSE() -> FALSE | K93: Q1
E94: 45839 | F94: 2025 | G94: 7 | H94: July | I94: Tuesday | J94: =FALSE() -> FALSE | K94: Q2
E95: 45840 | F95: 2025 | G95: 7 | H95: July | I95: Wednesday | J95: =FALSE() -> FALSE | K95: Q2
E96: 45841 | F96: 2025 | G96: 7 | H96: July | I96: Thursday | J96: =FALSE() -> FALSE | K96: Q2
E97: 45842 | F97: 2025 | G97: 7 | H97: July | I97: Friday | J97: =FALSE() -> FALSE | K97: Q2
E98: 45843 | F98: 2025 | G98: 7 | H98: July | I98: Saturday | J98: =TRUE() -> TRUE | K98: Q2
E99: 45844 | F99: 2025 | G99: 7 | H99: July | I99: Sunday | J99: =TRUE() -> TRUE | K99: Q2
E100: 45845 | F100: 2025 | G100: 7 | H100: July | I100: Monday | J100: =FALSE() -> FALSE | K100: Q2
...

Sheet Formula Reference
A1: 📐 FORMULA REFERENCE GUIDE — Market Research & Customer Segmentation Tool
A2: Formula / KPI | B2: Business Purpose | C2: Excel Formula Used | D2: Expected Output / Range
A3: Total Customers | B3: Count all unique customers | C3: ='KPI Summary'!B3 -> 200 | D3: Integer ≥ 1
A4: Total Revenue | B4: Sum all transaction amounts | C4: ='KPI Summary'!B11 -> 10038773 | D4: INR value
A5: Average Order Value | B5: Mean transaction value | C5: =AVERAGE(tblTransactions[Amount (INR)]) -> 9615.683 | D5: INR value
A6: RFM Recency | B6: Days since last purchase | C6: TODAY() - MAXIFS(tblTransactions[Date], tblTransactions[CustomerID], [@CustomerID]) | D6: Integer (days)
A7: RFM Frequency | B7: Number of transactions | C7: COUNTIFS(tblTransactions[CustomerID], [@CustomerID]) | D7: Integer ≥ 1
A8: RFM Monetary | B8: Total spend per customer | C8: SUMIFS(tblTransactions[Amount (INR)], tblTransactions[CustomerID], [@CustomerID]) | D8: INR value
A9: RFM Score | B9: Concatenated R+F+M scores | C9: TEXT(R_Score,"0") & TEXT(F_Score,"0") & TEXT(M_Score,"0") → e.g. "555" | D9: 3-digit string e.g. "555"
A10: Segment Assignment | B10: IFS-based segment label | C10: IFS(RFM_Score="555","Loyal", AND(Recency>90,Freq<3),"At Risk", Monetary>=50000,"High Value", TRUE,"General") | D10: Text label
A11: Satisfaction Index | B11: Blended satisfaction score | C11: AVERAGE( Satisfaction, RecommendationLikelihood / 2 ) | D11: 1.0–5.0
A12: Repeat Customer % | B12: Returning customers ratio | C12: COUNTIFS(CustomerType,"Returning") / COUNTA(CustomerID) | D12: 0%–100%
A13: At-Risk % | B13: At-risk customers ratio | C13: COUNTIFS(CustomerSegment,"At Risk") / COUNTA(CustomerID) | D13: 0%–100%
A14: AgeGroup | B14: Customer age classification | C14: IF(Age<25,"<25", IF(Age<40,"25-39", IF(Age<55,"40-54","55+"))) | D14: Text group
A15: IncomeBracket | B15: Income tier classification | C15: IF(IncomeRange<25000,"Low", IF(IncomeRange<75000,"Mid","High")) | D15: Low/Mid/High
A16: MonthsAsCustomer | B16: Tenure in months | C16: DATEDIF(JoinDate, TODAY(), "M") | D16: Integer months
A17: XLOOKUP usage | B17: Merge survey to RFM table | C17: XLOOKUP(CustomerID, tblSurvey[CustomerID], tblSurvey[Satisfaction]) | D17: Match value
... A20: Segment Revenue | B20: Revenue per segment | C20: SUMIFS(tblTransactions[Amount (INR)], tblTransactions[CustomerID], tblFinal[CustomerID], tblFinal[CustomerSegment], "Loyal") | D20: INR value
